{"Derivative(x(t), (t, 2))": "0", "Derivative(y(t), (t, 2))": "0", "Derivative(\u03b1(t), (t, 2))": "64*m*r**3*(-x3*sin(x1 - x6)*sin(x1)*sin(x2)**2*sin(x7)*sin(x5) - x3*sin(x1)*sin(x2)*cos(x7)*cos(x5) + x3*sin(x1)*sin(x7)*cos(x1 - x6)*cos(x2)*cos(x5) + x3*sin(x2)**2*sin(x7)*sin(x5)*cos(x6) + x3*sin(x2)*sin(x5)*cos(x1)*cos(x2)*cos(x7) + x3*sin(x7)*sin(x5)*cos(x1 - x6)*cos(x1) - x3*sin(x7)*sin(x5)*cos(x6) - x8*sin(x1)*sin(x2)*cos(x1 - x6)*cos(x2)*cos(x5) + x8*sin(x2)*sin(x6)*cos(x2)*cos(x5) - x8*sin(x2)*sin(x5)*cos(x1 - x6)*cos(x1) + sin(x1 - x6)*sin(x1)*sin(x2)*sin(x7)*cos(x2)*cos(x5) + sin(x1 - x6)*sin(x2)*sin(x7)*sin(x5)*cos(x1) + sin(x2)**2*cos(x1)*cos(x7)*cos(x5) - sin(x2)*sin(x7)*cos(x2)*cos(x6)*cos(x5))*sin(x2)*sin(x7)*diff(diff(x1, t), t)", "Derivative(\u03b2(t), (t, 2))": "64*m*r**3*(-x3*sin(x1 - x6)*sin(x1)*sin(x2)**2*sin(x7)*sin(x5) - x3*sin(x1)*sin(x2)*cos(x7)*cos(x5) + x3*sin(x1)*sin(x7)*cos(x1 - x6)*cos(x2)*cos(x5) + x3*sin(x2)**2*sin(x7)*sin(x5)*cos(x6) + x3*sin(x2)*sin(x5)*cos(x1)*cos(x2)*cos(x7) + x3*sin(x7)*sin(x5)*cos(x1 - x6)*cos(x1) - x3*sin(x7)*sin(x5)*cos(x6) - x8*sin(x1)*sin(x2)*cos(x1 - x6)*cos(x2)*cos(x5) + x8*sin(x2)*sin(x6)*cos(x2)*cos(x5) - x8*sin(x2)*sin(x5)*cos(x1 - x6)*cos(x1) + sin(x1 - x6)*sin(x1)*sin(x2)*sin(x7)*cos(x2)*cos(x5) + sin(x1 - x6)*sin(x2)*sin(x7)*sin(x5)*cos(x1) + sin(x2)**2*cos(x1)*cos(x7)*cos(x5) - sin(x2)*sin(x7)*cos(x2)*cos(x6)*cos(x5))*x3*sin(x7)*diff(diff(x2, t), t)", "Derivative(\u03b3(t), (t, 2))": "0", "Derivative(\u03c8(t), (t, 2))": "64*m*r**3*(-x3*sin(x1 - x6)*sin(x1)*sin(x2)**2*sin(x7)*sin(x5) - x3*sin(x1)*sin(x2)*cos(x7)*cos(x5) + x3*sin(x1)*sin(x7)*cos(x1 - x6)*cos(x2)*cos(x5) + x3*sin(x2)**2*sin(x7)*sin(x5)*cos(x6) + x3*sin(x2)*sin(x5)*cos(x1)*cos(x2)*cos(x7) + x3*sin(x7)*sin(x5)*cos(x1 - x6)*cos(x1) - x3*sin(x7)*sin(x5)*cos(x6) - x8*sin(x1)*sin(x2)*cos(x1 - x6)*cos(x2)*cos(x5) + x8*sin(x2)*sin(x6)*cos(x2)*cos(x5) - x8*sin(x2)*sin(x5)*cos(x1 - x6)*cos(x1) + sin(x1 - x6)*sin(x1)*sin(x2)*sin(x7)*cos(x2)*cos(x5) + sin(x1 - x6)*sin(x2)*sin(x7)*sin(x5)*cos(x1) + sin(x2)**2*cos(x1)*cos(x7)*cos(x5) - sin(x2)*sin(x7)*cos(x2)*cos(x6)*cos(x5))*sin(x7)*diff(diff(x5, t), t)", "Derivative(x(t), t)*Derivative(y(t), t)": "128*C_mz*m*(2*x3**2*sin(x1 - x6)*sin(x1)*sin(x2)**2*cos(x1)*cos(x5) - 2*x3**2*sin(x1)**2*sin(x2)**2*cos(x1 - x6)*cos(x7)*cos(x5) + x3**2*sin(x1)**2*sin(x2)*sin(x7)*cos(x2)*cos(x5) + x3**2*sin(x1)*sin(x2)**2*sin(x6)*cos(x7)*cos(x5) - x3**2*sin(x2)**2*cos(x1)*cos(x6)*cos(x5) - x3*x8*sin(x1 - x6)*sin(x1)*sin(x2)**3*sin(x7)*cos(x1)*cos(x5) + x3*x8*sin(x2)**3*sin(x7)*cos(x1)*cos(x6)*cos(x5) + x3*x8*sin(x2)**2*cos(x1)**2*cos(x2)*cos(x7)*cos(x5) - x3*sin(x1 - x6)*sin(x1)**2*sin(x2)**3*cos(x7)*cos(x5) + 2*x3*sin(x1 - x6)*sin(x1)**2*sin(x2)*cos(x5) + 2*x3*sin(x1 - x6)*sin(x1)*sin(x2)*sin(x5)*cos(x1)*cos(x2) - 2*x3*sin(x1)**2*sin(x2)*sin(x5)*cos(x1 - x6)*cos(x2)*cos(x7) + x3*sin(x1)**2*sin(x7)*sin(x5)*cos(x2)**2 - x3*sin(x1)*sin(x2)**3*cos(x1 - x6)*cos(x1)*cos(x5) + x3*sin(x1)*sin(x2)**3*cos(x6)*cos(x7)*cos(x5) - x3*sin(x1)*sin(x2)**2*sin(x7)*cos(x1)*cos(x2)*cos(x5) + x3*sin(x1)*sin(x2)*sin(x6)*sin(x5)*cos(x2)*cos(x7) + 2*x3*sin(x1)*sin(x2)*cos(x1 - x6)*cos(x1)*cos(x7)*cos(x5) - x3*sin(x1)*sin(x2)*cos(x6)*cos(x5) - x3*sin(x1)*sin(x7)*cos(x1)*cos(x2)*cos(x5) + x3*sin(x2)**3*sin(x6)*cos(x1)*cos(x5) - x3*sin(x2)*sin(x6)*cos(x1)*cos(x7)*cos(x5) - x3*sin(x2)*sin(x5)*cos(x1)*cos(x2)*cos(x6) - x8*sin(x1 - x6)*sin(x1)**2*sin(x2)**2*sin(x7)*cos(x5) - x8*sin(x1 - x6)*sin(x1)*sin(x2)**2*sin(x7)*sin(x5)*cos(x1)*cos(x2) + x8*sin(x1)*sin(x2)**2*sin(x7)*cos(x6)*cos(x5) + x8*sin(x1)*sin(x2)*cos(x1)*cos(x2)*cos(x7)*cos(x5) + x8*sin(x2)**2*sin(x7)*sin(x5)*cos(x1)*cos(x2)*cos(x6) + x8*sin(x2)*sin(x5)*cos(x1)**2*cos(x2)**2*cos(x7) - sin(x1 - x6)*sin(x1)**2*sin(x2)**2*sin(x5)*cos(x2)*cos(x7) + sin(x1 - x6)*sin(x1)*sin(x2)**2*cos(x1)*cos(x7)*cos(x5) - sin(x1)**2*sin(x2)**2*cos(x1 - x6)*cos(x5) + sin(x1)*sin(x2)**2*sin(x6)*cos(x5) - sin(x1)*sin(x2)**2*sin(x5)*cos(x1 - x6)*cos(x1)*cos(x2) + sin(x1)*sin(x2)**2*sin(x5)*cos(x2)*cos(x6)*cos(x7) - sin(x1)*sin(x2)*sin(x7)*sin(x5)*cos(x1)*cos(x2)**2 + sin(x2)**2*sin(x6)*sin(x5)*cos(x1)*cos(x2) - sin(x2)**2*cos(x1)*cos(x6)*cos(x7)*cos(x5) + sin(x2)*sin(x7)*cos(x1)**2*cos(x2)*cos(x5))*sin(x7)*diff(x, t)*diff(y, t)", "Derivative(x(t), t)*Derivative(\u03b1(t), t)": "32*m*(8*C_mz**2*x3**2*sin(x1 - x6)*sin(x1)*sin(x5)*cos(x2) - 4*C_mz**2*x3**2*sin(x5)*cos(x2)*cos(x6) - 4*C_mz**2*x3*x8*sin(x1 - x6)*sin(x1)*sin(x2)*sin(x7)*sin(x5)*cos(x2) + 4*C_mz**2*x3*x8*sin(x2)*sin(x7)*sin(x5)*cos(x2)*cos(x6) + 4*C_mz**2*x3*x8*sin(x5)*cos(x1)*cos(x2)**2*cos(x7) + 8*C_mz**2*x3*sin(x1 - x6)*sin(x1)*sin(x2)*cos(x5) - 4*C_mz**2*x3*sin(x1)*sin(x2)*sin(x5)*cos(x1 - x6)*cos(x2) + 4*C_mz**2*x3*sin(x2)*sin(x6)*sin(x5)*cos(x2) - 4*C_mz**2*x3*sin(x2)*cos(x6)*cos(x5) - 4*C_mz**2*x8*sin(x1 - x6)*sin(x1)*sin(x2)**2*sin(x7)*cos(x5) + 4*C_mz**2*x8*sin(x2)**2*sin(x7)*cos(x6)*cos(x5) + 4*C_mz**2*x8*sin(x2)*cos(x1)*cos(x2)*cos(x7)*cos(x5) - 4*C_mz**2*sin(x1)*sin(x2)**2*cos(x1 - x6)*cos(x5) + 4*C_mz**2*sin(x2)**2*sin(x6)*cos(x5) + 8*C_mz*R*x3**2*sin(x1 - x6)*sin(x1)**2*sin(x2)*sin(x7)*cos(x5) - 4*C_mz*R*x3**2*sin(x1)*sin(x2)*sin(x7)*cos(x6)*cos(x5) + 4*C_mz*R*x3*x8*sin(x1)*sin(x2)**2*cos(x1 - x6)*cos(x1)*cos(x5) + 8*C_mz*R*x3*sin(x1 - x6)*sin(x1)**2*sin(x7)*sin(x5)*cos(x2) - 4*C_mz*R*x3*sin(x1 - x6)*sin(x1)*sin(x2)**2*sin(x7)*cos(x1)*cos(x5) - 8*C_mz*R*x3*sin(x1)**2*sin(x7)*cos(x1 - x6)*cos(x5) + 8*C_mz*R*x3*sin(x1)*sin(x6)*sin(x7)*cos(x5) - 4*C_mz*R*x3*sin(x1)*sin(x7)*sin(x5)*cos(x2)*cos(x6) + 4*C_mz*R*x3*sin(x7)*cos(x1)*cos(x6)*cos(x5) + 4*C_mz*R*x8*sin(x1)**2*sin(x2)*cos(x1 - x6)*cos(x5) + 4*C_mz*R*x8*sin(x1)*sin(x2)*sin(x5)*cos(x1 - x6)*cos(x1)*cos(x2) - 4*C_mz*R*x8*sin(x2)*cos(x1 - x6)*cos(x5) - 4*C_mz*R*sin(x1 - x6)*sin(x1)**2*sin(x2)*sin(x7)*cos(x5) - 4*C_mz*R*sin(x1 - x6)*sin(x1)*sin(x2)*sin(x7)*sin(x5)*cos(x1)*cos(x2) + 4*C_mz*R*sin(x1 - x6)*sin(x2)*sin(x7)*cos(x5) + 8*l**2*x3**2*sin(x1 - x6)*sin(x1)*sin(x5)*cos(x2) - 4*l**2*x3**2*sin(x5)*cos(x2)*cos(x6) - 4*l**2*x3*x8*sin(x1 - x6)*sin(x1)*sin(x2)*sin(x7)*sin(x5)*cos(x2) + 4*l**2*x3*x8*sin(x2)*sin(x7)*sin(x5)*cos(x2)*cos(x6) + 4*l**2*x3*x8*sin(x5)*cos(x1)*cos(x2)**2*cos(x7) + 8*l**2*x3*sin(x1 - x6)*sin(x1)*sin(x2)*cos(x5) - 4*l**2*x3*sin(x1)*sin(x2)*sin(x5)*cos(x1 - x6)*cos(x2) + 4*l**2*x3*sin(x2)*sin(x6)*sin(x5)*cos(x2) - 4*l**2*x3*sin(x2)*cos(x6)*cos(x5) - 4*l**2*x8*sin(x1 - x6)*sin(x1)*sin(x2)**2*sin(x7)*cos(x5) + 4*l**2*x8*sin(x2)**2*sin(x7)*cos(x6)*cos(x5) + 4*l**2*x8*sin(x2)*cos(x1)*cos(x2)*cos(x7)*cos(x5) - 4*l**2*sin(x1)*sin(x2)**2*cos(x1 - x6)*cos(x5) + 4*l**2*sin(x2)**2*sin(x6)*cos(x5) + 2*r**2*x3**2*sin(x1 - x6)*sin(x1)*sin(x5)*cos(x2) - r**2*x3**2*sin(x5)*cos(x2)*cos(x6) - r**2*x3*x8*sin(x1 - x6)*sin(x1)*sin(x2)*sin(x7)*sin(x5)*cos(x2) + r**2*x3*x8*sin(x2)*sin(x7)*sin(x5)*cos(x2)*cos(x6) + r**2*x3*x8*sin(x5)*cos(x1)*cos(x2)**2*cos(x7) + 2*r**2*x3*sin(x1 - x6)*sin(x1)*sin(x2)*cos(x5) - r**2*x3*sin(x1)*sin(x2)*sin(x5)*cos(x1 - x6)*cos(x2) + r**2*x3*sin(x2)*sin(x6)*sin(x5)*cos(x2) - r**2*x3*sin(x2)*cos(x6)*cos(x5) - r**2*x8*sin(x1 - x6)*sin(x1)*sin(x2)**2*sin(x7)*cos(x5) + r**2*x8*sin(x2)**2*sin(x7)*cos(x6)*cos(x5) + r**2*x8*sin(x2)*cos(x1)*cos(x2)*cos(x7)*cos(x5) - r**2*sin(x1)*sin(x2)**2*cos(x1 - x6)*cos(x5) + r**2*sin(x2)**2*sin(x6)*cos(x5))*sin(x2)*sin(x7)*diff(x, t)*diff(x1, t)", "Derivative(x(t), t)*Derivative(\u03b2(t), t)": "32*m*(-8*C_mz**2*x3*sin(x1 - x6)*sin(x1)*sin(x2)*sin(x5) + 4*C_mz**2*x3*sin(x2)*sin(x5)*cos(x6) + 4*C_mz**2*x8*sin(x1 - x6)*sin(x1)*sin(x2)**2*sin(x7)*sin(x5) - 4*C_mz**2*x8*sin(x2)**2*sin(x7)*sin(x5)*cos(x6) - 4*C_mz**2*x8*sin(x2)*sin(x5)*cos(x1)*cos(x2)*cos(x7) + 4*C_mz**2*sin(x1)*sin(x2)**2*sin(x5)*cos(x1 - x6) - 4*C_mz**2*sin(x2)**2*sin(x6)*sin(x5) + 4*C_mz*R*x3**2*sin(x1)**2*sin(x2)**2*cos(x7)*cos(x5) - 4*C_mz*R*x3**2*sin(x1)**2*sin(x2)*sin(x7)*cos(x1 - x6)*cos(x2)*cos(x5) + 4*C_mz*R*x3*x8*sin(x1)**2*sin(x2)**2*cos(x1 - x6)*cos(x2)*cos(x5) - 4*C_mz*R*x3*x8*sin(x1)*sin(x2)**2*sin(x6)*cos(x2)*cos(x5) - 4*C_mz*R*x3*sin(x1 - x6)*sin(x1)**2*sin(x2)**2*sin(x7)*cos(x2)*cos(x5) + 4*C_mz*R*x3*sin(x1)**2*sin(x2)**2*sin(x7)*sin(x5)*cos(x1 - x6) + 4*C_mz*R*x3*sin(x1)**2*sin(x2)*sin(x5)*cos(x2)*cos(x7) - 4*C_mz*R*x3*sin(x1)**2*sin(x7)*sin(x5)*cos(x1 - x6) - 4*C_mz*R*x3*sin(x1)*sin(x2)**3*cos(x1)*cos(x7)*cos(x5) + 4*C_mz*R*x3*sin(x1)*sin(x2)**2*sin(x7)*cos(x2)*cos(x6)*cos(x5) - 4*C_mz*R*x3*sin(x1)*sin(x2)*cos(x1)*cos(x7)*cos(x5) + 4*C_mz*R*x3*sin(x1)*sin(x7)*cos(x1 - x6)*cos(x1)*cos(x2)*cos(x5) - 4*C_mz*R*x8*sin(x1)**2*sin(x2)**3*sin(x5)*cos(x1 - x6) + 4*C_mz*R*x8*sin(x1)**2*sin(x2)*sin(x5)*cos(x1 - x6) + 4*C_mz*R*x8*sin(x1)*sin(x2)**3*sin(x6)*sin(x5) - 4*C_mz*R*x8*sin(x1)*sin(x2)*sin(x6)*sin(x5) - 4*C_mz*R*x8*sin(x1)*sin(x2)*cos(x1 - x6)*cos(x1)*cos(x2)*cos(x5) + 4*C_mz*R*x8*sin(x2)*sin(x6)*cos(x1)*cos(x2)*cos(x5) + 4*C_mz*R*sin(x1 - x6)*sin(x1)**2*sin(x2)**3*sin(x7)*sin(x5) - 4*C_mz*R*sin(x1 - x6)*sin(x1)**2*sin(x2)*sin(x7)*sin(x5) + 4*C_mz*R*sin(x1 - x6)*sin(x1)*sin(x2)*sin(x7)*cos(x1)*cos(x2)*cos(x5) - 4*C_mz*R*sin(x1)**2*sin(x2)**2*cos(x7)*cos(x5) - 4*C_mz*R*sin(x1)*sin(x2)**3*sin(x7)*sin(x5)*cos(x6) - 4*C_mz*R*sin(x1)*sin(x2)**2*sin(x5)*cos(x1)*cos(x2)*cos(x7) + 4*C_mz*R*sin(x1)*sin(x2)*sin(x7)*sin(x5)*cos(x6) + 4*C_mz*R*sin(x2)**2*cos(x7)*cos(x5) - 4*C_mz*R*sin(x2)*sin(x7)*cos(x1)*cos(x2)*cos(x6)*cos(x5) - 8*l**2*x3*sin(x1 - x6)*sin(x1)*sin(x2)*sin(x5) + 4*l**2*x3*sin(x2)*sin(x5)*cos(x6) + 4*l**2*x8*sin(x1 - x6)*sin(x1)*sin(x2)**2*sin(x7)*sin(x5) - 4*l**2*x8*sin(x2)**2*sin(x7)*sin(x5)*cos(x6) - 4*l**2*x8*sin(x2)*sin(x5)*cos(x1)*cos(x2)*cos(x7) + 4*l**2*sin(x1)*sin(x2)**2*sin(x5)*cos(x1 - x6) - 4*l**2*sin(x2)**2*sin(x6)*sin(x5) - 2*r**2*x3*sin(x1 - x6)*sin(x1)*sin(x2)*sin(x5) + r**2*x3*sin(x2)*sin(x5)*cos(x6) + r**2*x8*sin(x1 - x6)*sin(x1)*sin(x2)**2*sin(x7)*sin(x5) - r**2*x8*sin(x2)**2*sin(x7)*sin(x5)*cos(x6) - r**2*x8*sin(x2)*sin(x5)*cos(x1)*cos(x2)*cos(x7) + r**2*sin(x1)*sin(x2)**2*sin(x5)*cos(x1 - x6) - r**2*sin(x2)**2*sin(x6)*sin(x5))*sin(x7)*diff(x, t)*diff(x2, t)", "Derivative(x(t), t)*Derivative(\u03b3(t), t)": "32*m*(8*C_mz**2*x3*sin(x1 - x6)*sin(x1)*sin(x2)*cos(x5) - 4*C_mz**2*x3*sin(x2)*cos(x6)*cos(x5) - 4*C_mz**2*x8*sin(x1 - x6)*sin(x1)*sin(x2)**2*sin(x7)*cos(x5) + 4*C_mz**2*x8*sin(x2)**2*sin(x7)*cos(x6)*cos(x5) + 4*C_mz**2*x8*sin(x2)*cos(x1)*cos(x2)*cos(x7)*cos(x5) - 4*C_mz**2*sin(x1)*sin(x2)**2*cos(x1 - x6)*cos(x5) + 4*C_mz**2*sin(x2)**2*sin(x6)*cos(x5) + 4*C_mz*R*x3**2*sin(x1 - x6)*sin(x1)**2*sin(x2)**3*sin(x7)*cos(x5) - 4*C_mz*R*x3**2*sin(x1)*sin(x2)**3*sin(x7)*cos(x6)*cos(x5) - 4*C_mz*R*x3**2*sin(x1)*sin(x2)**2*cos(x1)*cos(x2)*cos(x7)*cos(x5) - 4*C_mz*R*x3**2*sin(x1)*sin(x2)*sin(x7)*cos(x1 - x6)*cos(x1)*cos(x5) + 4*C_mz*R*x3**2*sin(x1)*sin(x2)*sin(x7)*cos(x6)*cos(x5) + 4*C_mz*R*x3*x8*sin(x1)*sin(x2)**2*cos(x1 - x6)*cos(x1)*cos(x5) + 4*C_mz*R*x3*sin(x1 - x6)*sin(x1)**2*sin(x2)**2*sin(x7)*sin(x5)*cos(x2) - 8*C_mz*R*x3*sin(x1 - x6)*sin(x1)*sin(x2)**2*sin(x7)*cos(x1)*cos(x5) - 4*C_mz*R*x3*sin(x1)**2*sin(x2)*cos(x2)*cos(x7)*cos(x5) - 4*C_mz*R*x3*sin(x1)**2*sin(x7)*cos(x1 - x6)*cos(x5) + 4*C_mz*R*x3*sin(x1)*sin(x2)**3*sin(x5)*cos(x1)*cos(x7) - 4*C_mz*R*x3*sin(x1)*sin(x2)**2*sin(x7)*sin(x5)*cos(x2)*cos(x6) - 4*C_mz*R*x3*sin(x1)*sin(x2)*sin(x5)*cos(x1)*cos(x7) + 4*C_mz*R*x3*sin(x1)*sin(x6)*sin(x7)*cos(x5) - 4*C_mz*R*x3*sin(x1)*sin(x7)*sin(x5)*cos(x1 - x6)*cos(x1)*cos(x2) + 4*C_mz*R*x3*sin(x1)*sin(x7)*sin(x5)*cos(x2)*cos(x6) + 4*C_mz*R*x3*sin(x2)**2*sin(x7)*cos(x1)*cos(x6)*cos(x5) + 4*C_mz*R*x3*sin(x2)*cos(x2)*cos(x7)*cos(x5) + 4*C_mz*R*x8*sin(x1)**2*sin(x2)*cos(x1 - x6)*cos(x5) + 4*C_mz*R*x8*sin(x1)*sin(x2)*sin(x5)*cos(x1 - x6)*cos(x1)*cos(x2) - 4*C_mz*R*x8*sin(x2)*cos(x1 - x6)*cos(x5) - 4*C_mz*R*sin(x1 - x6)*sin(x1)**2*sin(x2)*sin(x7)*cos(x5) - 4*C_mz*R*sin(x1 - x6)*sin(x1)*sin(x2)*sin(x7)*sin(x5)*cos(x1)*cos(x2) + 4*C_mz*R*sin(x1 - x6)*sin(x2)*sin(x7)*cos(x5) + 8*l**2*x3*sin(x1 - x6)*sin(x1)*sin(x2)*cos(x5) - 4*l**2*x3*sin(x2)*cos(x6)*cos(x5) - 4*l**2*x8*sin(x1 - x6)*sin(x1)*sin(x2)**2*sin(x7)*cos(x5) + 4*l**2*x8*sin(x2)**2*sin(x7)*cos(x6)*cos(x5) + 4*l**2*x8*sin(x2)*cos(x1)*cos(x2)*cos(x7)*cos(x5) - 4*l**2*sin(x1)*sin(x2)**2*cos(x1 - x6)*cos(x5) + 4*l**2*sin(x2)**2*sin(x6)*cos(x5) + 2*r**2*x3*sin(x1 - x6)*sin(x1)*sin(x2)*cos(x5) - r**2*x3*sin(x2)*cos(x6)*cos(x5) - r**2*x8*sin(x1 - x6)*sin(x1)*sin(x2)**2*sin(x7)*cos(x5) + r**2*x8*sin(x2)**2*sin(x7)*cos(x6)*cos(x5) + r**2*x8*sin(x2)*cos(x1)*cos(x2)*cos(x7)*cos(x5) - r**2*sin(x1)*sin(x2)**2*cos(x1 - x6)*cos(x5) + r**2*sin(x2)**2*sin(x6)*cos(x5))*sin(x7)*diff(x, t)*diff(x3, t)", "Derivative(x(t), t)*Derivative(\u03c8(t), t)": "0", "Derivative(y(t), t)*Derivative(\u03b1(t), t)": "32*m*(8*C_mz**2*x3**2*sin(x1)*sin(x2)*sin(x5)*cos(x1 - x6)*cos(x2)*cos(x7) - 4*C_mz**2*x3**2*sin(x1)*sin(x7)*sin(x5)*cos(x2)**2 - 4*C_mz**2*x3**2*sin(x2)*sin(x6)*sin(x5)*cos(x2)*cos(x7) + 4*C_mz**2*x3*sin(x1 - x6)*sin(x1)*sin(x2)**2*sin(x5)*cos(x2)*cos(x7) + 8*C_mz**2*x3*sin(x1)*sin(x2)**2*cos(x1 - x6)*cos(x7)*cos(x5) - 4*C_mz**2*x3*sin(x1)*sin(x2)*sin(x7)*cos(x2)*cos(x5) - 4*C_mz**2*x3*sin(x2)**2*sin(x6)*cos(x7)*cos(x5) - 4*C_mz**2*x3*sin(x2)**2*sin(x5)*cos(x2)*cos(x6)*cos(x7) + 4*C_mz**2*x3*sin(x2)*sin(x7)*sin(x5)*cos(x1)*cos(x2)**2 + 4*C_mz**2*sin(x1 - x6)*sin(x1)*sin(x2)**3*cos(x7)*cos(x5) - 4*C_mz**2*sin(x2)**3*cos(x6)*cos(x7)*cos(x5) + 4*C_mz**2*sin(x2)**2*sin(x7)*cos(x1)*cos(x2)*cos(x5) - 8*C_mz*R*x3**2*sin(x1)**2*sin(x2)**2*sin(x7)*cos(x1 - x6)*cos(x5) + 8*C_mz*R*x3**2*sin(x1)*sin(x2)**2*sin(x6)*sin(x7)*cos(x5) + 4*C_mz*R*x3**2*sin(x2)**2*sin(x7)*cos(x1)*cos(x6)*cos(x5) + 4*C_mz*R*x3*x8*sin(x1)**2*sin(x2)**3*cos(x1 - x6)*cos(x5) - 4*C_mz*R*x3*x8*sin(x2)**3*cos(x1 - x6)*cos(x5) - 4*C_mz*R*x3*sin(x1 - x6)*sin(x1)**2*sin(x2)**3*sin(x7)*cos(x5) - 8*C_mz*R*x3*sin(x1 - x6)*sin(x1)**2*sin(x2)*sin(x7)*cos(x5) + 4*C_mz*R*x3*sin(x1 - x6)*sin(x2)**3*sin(x7)*cos(x5) - 8*C_mz*R*x3*sin(x1)**2*sin(x2)*sin(x7)*sin(x5)*cos(x1 - x6)*cos(x2) + 8*C_mz*R*x3*sin(x1)*sin(x2)*sin(x6)*sin(x7)*sin(x5)*cos(x2) + 4*C_mz*R*x3*sin(x1)*sin(x2)*sin(x7)*cos(x6)*cos(x5) + 4*C_mz*R*x3*sin(x2)*sin(x7)*sin(x5)*cos(x1)*cos(x2)*cos(x6) + 4*C_mz*R*x8*sin(x1)**2*sin(x2)**2*sin(x5)*cos(x1 - x6)*cos(x2) - 4*C_mz*R*x8*sin(x1)*sin(x2)**2*cos(x1 - x6)*cos(x1)*cos(x5) - 4*C_mz*R*x8*sin(x2)**2*sin(x5)*cos(x1 - x6)*cos(x2) - 4*C_mz*R*sin(x1 - x6)*sin(x1)**2*sin(x2)**2*sin(x7)*sin(x5)*cos(x2) + 4*C_mz*R*sin(x1 - x6)*sin(x1)*sin(x2)**2*sin(x7)*cos(x1)*cos(x5) + 4*C_mz*R*sin(x1 - x6)*sin(x2)**2*sin(x7)*sin(x5)*cos(x2) + 8*l**2*x3**2*sin(x1)*sin(x2)*sin(x5)*cos(x1 - x6)*cos(x2)*cos(x7) - 4*l**2*x3**2*sin(x1)*sin(x7)*sin(x5)*cos(x2)**2 - 4*l**2*x3**2*sin(x2)*sin(x6)*sin(x5)*cos(x2)*cos(x7) + 4*l**2*x3*sin(x1 - x6)*sin(x1)*sin(x2)**2*sin(x5)*cos(x2)*cos(x7) + 8*l**2*x3*sin(x1)*sin(x2)**2*cos(x1 - x6)*cos(x7)*cos(x5) - 4*l**2*x3*sin(x1)*sin(x2)*sin(x7)*cos(x2)*cos(x5) - 4*l**2*x3*sin(x2)**2*sin(x6)*cos(x7)*cos(x5) - 4*l**2*x3*sin(x2)**2*sin(x5)*cos(x2)*cos(x6)*cos(x7) + 4*l**2*x3*sin(x2)*sin(x7)*sin(x5)*cos(x1)*cos(x2)**2 + 4*l**2*sin(x1 - x6)*sin(x1)*sin(x2)**3*cos(x7)*cos(x5) - 4*l**2*sin(x2)**3*cos(x6)*cos(x7)*cos(x5) + 4*l**2*sin(x2)**2*sin(x7)*cos(x1)*cos(x2)*cos(x5) + 2*r**2*x3**2*sin(x1)*sin(x2)*sin(x5)*cos(x1 - x6)*cos(x2)*cos(x7) - r**2*x3**2*sin(x1)*sin(x7)*sin(x5)*cos(x2)**2 - r**2*x3**2*sin(x2)*sin(x6)*sin(x5)*cos(x2)*cos(x7) + r**2*x3*sin(x1 - x6)*sin(x1)*sin(x2)**2*sin(x5)*cos(x2)*cos(x7) + 2*r**2*x3*sin(x1)*sin(x2)**2*cos(x1 - x6)*cos(x7)*cos(x5) - r**2*x3*sin(x1)*sin(x2)*sin(x7)*cos(x2)*cos(x5) - r**2*x3*sin(x2)**2*sin(x6)*cos(x7)*cos(x5) - r**2*x3*sin(x2)**2*sin(x5)*cos(x2)*cos(x6)*cos(x7) + r**2*x3*sin(x2)*sin(x7)*sin(x5)*cos(x1)*cos(x2)**2 + r**2*sin(x1 - x6)*sin(x1)*sin(x2)**3*cos(x7)*cos(x5) - r**2*sin(x2)**3*cos(x6)*cos(x7)*cos(x5) + r**2*sin(x2)**2*sin(x7)*cos(x1)*cos(x2)*cos(x5))*sin(x7)*diff(y, t)*diff(x1, t)", "Derivative(y(t), t)*Derivative(\u03b2(t), t)": "32*m*(-8*C_mz**2*x3*sin(x1)*sin(x2)*sin(x5)*cos(x1 - x6)*cos(x7) + 4*C_mz**2*x3*sin(x1)*sin(x7)*sin(x5)*cos(x2) + 4*C_mz**2*x3*sin(x2)*sin(x6)*sin(x5)*cos(x7) - 4*C_mz**2*sin(x1 - x6)*sin(x1)*sin(x2)**2*sin(x5)*cos(x7) + 4*C_mz**2*sin(x2)**2*sin(x5)*cos(x6)*cos(x7) - 4*C_mz**2*sin(x2)*sin(x7)*sin(x5)*cos(x1)*cos(x2) - 4*C_mz*R*x3**2*sin(x1)*sin(x2)**2*cos(x1)*cos(x7)*cos(x5) + 4*C_mz*R*x3**2*sin(x1)*sin(x2)*sin(x7)*cos(x1 - x6)*cos(x1)*cos(x2)*cos(x5) - 4*C_mz*R*x3*x8*sin(x1)*sin(x2)**2*cos(x1 - x6)*cos(x1)*cos(x2)*cos(x5) + 4*C_mz*R*x3*x8*sin(x2)**2*sin(x6)*cos(x1)*cos(x2)*cos(x5) + 4*C_mz*R*x3*sin(x1 - x6)*sin(x1)*sin(x2)**2*sin(x7)*cos(x1)*cos(x2)*cos(x5) - 4*C_mz*R*x3*sin(x1)**2*sin(x2)**3*cos(x7)*cos(x5) - 4*C_mz*R*x3*sin(x1)**2*sin(x2)*cos(x7)*cos(x5) + 4*C_mz*R*x3*sin(x1)**2*sin(x7)*cos(x1 - x6)*cos(x2)*cos(x5) - 4*C_mz*R*x3*sin(x1)*sin(x2)**2*sin(x7)*sin(x5)*cos(x1 - x6)*cos(x1) - 4*C_mz*R*x3*sin(x1)*sin(x2)*sin(x5)*cos(x1)*cos(x2)*cos(x7) + 4*C_mz*R*x3*sin(x1)*sin(x7)*sin(x5)*cos(x1 - x6)*cos(x1) + 4*C_mz*R*x3*sin(x2)**3*cos(x7)*cos(x5) - 4*C_mz*R*x3*sin(x2)**2*sin(x7)*cos(x1)*cos(x2)*cos(x6)*cos(x5) - 4*C_mz*R*x8*sin(x1)**2*sin(x2)*cos(x1 - x6)*cos(x2)*cos(x5) + 4*C_mz*R*x8*sin(x1)*sin(x2)**3*sin(x5)*cos(x1 - x6)*cos(x1) + 4*C_mz*R*x8*sin(x1)*sin(x2)*sin(x6)*cos(x2)*cos(x5) - 4*C_mz*R*x8*sin(x1)*sin(x2)*sin(x5)*cos(x1 - x6)*cos(x1) - 4*C_mz*R*x8*sin(x2)**3*sin(x6)*sin(x5)*cos(x1) + 4*C_mz*R*x8*sin(x2)*sin(x6)*sin(x5)*cos(x1) + 4*C_mz*R*sin(x1 - x6)*sin(x1)**2*sin(x2)*sin(x7)*cos(x2)*cos(x5) - 4*C_mz*R*sin(x1 - x6)*sin(x1)*sin(x2)**3*sin(x7)*sin(x5)*cos(x1) + 4*C_mz*R*sin(x1 - x6)*sin(x1)*sin(x2)*sin(x7)*sin(x5)*cos(x1) - 4*C_mz*R*sin(x1)**2*sin(x2)**2*sin(x5)*cos(x2)*cos(x7) + 4*C_mz*R*sin(x1)*sin(x2)**2*cos(x1)*cos(x7)*cos(x5) - 4*C_mz*R*sin(x1)*sin(x2)*sin(x7)*cos(x2)*cos(x6)*cos(x5) + 4*C_mz*R*sin(x2)**3*sin(x7)*sin(x5)*cos(x1)*cos(x6) + 4*C_mz*R*sin(x2)**2*sin(x5)*cos(x2)*cos(x7) - 4*C_mz*R*sin(x2)*sin(x7)*sin(x5)*cos(x1)*cos(x6) - 8*l**2*x3*sin(x1)*sin(x2)*sin(x5)*cos(x1 - x6)*cos(x7) + 4*l**2*x3*sin(x1)*sin(x7)*sin(x5)*cos(x2) + 4*l**2*x3*sin(x2)*sin(x6)*sin(x5)*cos(x7) - 4*l**2*sin(x1 - x6)*sin(x1)*sin(x2)**2*sin(x5)*cos(x7) + 4*l**2*sin(x2)**2*sin(x5)*cos(x6)*cos(x7) - 4*l**2*sin(x2)*sin(x7)*sin(x5)*cos(x1)*cos(x2) - 2*r**2*x3*sin(x1)*sin(x2)*sin(x5)*cos(x1 - x6)*cos(x7) + r**2*x3*sin(x1)*sin(x7)*sin(x5)*cos(x2) + r**2*x3*sin(x2)*sin(x6)*sin(x5)*cos(x7) - r**2*sin(x1 - x6)*sin(x1)*sin(x2)**2*sin(x5)*cos(x7) + r**2*sin(x2)**2*sin(x5)*cos(x6)*cos(x7) - r**2*sin(x2)*sin(x7)*sin(x5)*cos(x1)*cos(x2))*sin(x7)*diff(y, t)*diff(x2, t)", "Derivative(y(t), t)*Derivative(\u03b3(t), t)": "32*m*(8*C_mz**2*x3*sin(x1)*sin(x2)*cos(x1 - x6)*cos(x7)*cos(x5) - 4*C_mz**2*x3*sin(x1)*sin(x7)*cos(x2)*cos(x5) - 4*C_mz**2*x3*sin(x2)*sin(x6)*cos(x7)*cos(x5) + 4*C_mz**2*sin(x1 - x6)*sin(x1)*sin(x2)**2*cos(x7)*cos(x5) - 4*C_mz**2*sin(x2)**2*cos(x6)*cos(x7)*cos(x5) + 4*C_mz**2*sin(x2)*sin(x7)*cos(x1)*cos(x2)*cos(x5) - 4*C_mz*R*x3**2*sin(x1 - x6)*sin(x1)*sin(x2)**3*sin(x7)*cos(x1)*cos(x5) - 4*C_mz*R*x3**2*sin(x1)**2*sin(x2)**2*cos(x2)*cos(x7)*cos(x5) - 4*C_mz*R*x3**2*sin(x1)**2*sin(x2)*sin(x7)*cos(x1 - x6)*cos(x5) + 4*C_mz*R*x3**2*sin(x1)*sin(x2)*sin(x6)*sin(x7)*cos(x5) + 4*C_mz*R*x3**2*sin(x2)**3*sin(x7)*cos(x1)*cos(x6)*cos(x5) + 4*C_mz*R*x3**2*sin(x2)**2*cos(x2)*cos(x7)*cos(x5) + 4*C_mz*R*x3*x8*sin(x1)**2*sin(x2)**2*cos(x1 - x6)*cos(x5) - 4*C_mz*R*x3*x8*sin(x2)**2*cos(x1 - x6)*cos(x5) - 8*C_mz*R*x3*sin(x1 - x6)*sin(x1)**2*sin(x2)**2*sin(x7)*cos(x5) - 4*C_mz*R*x3*sin(x1 - x6)*sin(x1)*sin(x2)**2*sin(x7)*sin(x5)*cos(x1)*cos(x2) + 4*C_mz*R*x3*sin(x1)**2*sin(x2)**3*sin(x5)*cos(x7) - 4*C_mz*R*x3*sin(x1)**2*sin(x2)*sin(x5)*cos(x7) - 4*C_mz*R*x3*sin(x1)**2*sin(x7)*sin(x5)*cos(x1 - x6)*cos(x2) + 8*C_mz*R*x3*sin(x1)*sin(x2)**2*sin(x7)*cos(x6)*cos(x5) + 4*C_mz*R*x3*sin(x1)*sin(x2)*cos(x1)*cos(x2)*cos(x7)*cos(x5) + 4*C_mz*R*x3*sin(x1)*sin(x6)*sin(x7)*sin(x5)*cos(x2) + 4*C_mz*R*x3*sin(x1)*sin(x7)*cos(x1 - x6)*cos(x1)*cos(x5) - 4*C_mz*R*x3*sin(x1)*sin(x7)*cos(x6)*cos(x5) - 4*C_mz*R*x3*sin(x2)**3*sin(x5)*cos(x7) - 4*C_mz*R*x3*sin(x2)**2*sin(x6)*sin(x7)*cos(x1)*cos(x5) + 4*C_mz*R*x3*sin(x2)**2*sin(x7)*sin(x5)*cos(x1)*cos(x2)*cos(x6) + 4*C_mz*R*x3*sin(x2)*sin(x5)*cos(x7) + 4*C_mz*R*x8*sin(x1)**2*sin(x2)*sin(x5)*cos(x1 - x6)*cos(x2) - 4*C_mz*R*x8*sin(x1)*sin(x2)*cos(x1 - x6)*cos(x1)*cos(x5) - 4*C_mz*R*x8*sin(x2)*sin(x5)*cos(x1 - x6)*cos(x2) - 4*C_mz*R*sin(x1 - x6)*sin(x1)**2*sin(x2)*sin(x7)*sin(x5)*cos(x2) + 4*C_mz*R*sin(x1 - x6)*sin(x1)*sin(x2)*sin(x7)*cos(x1)*cos(x5) + 4*C_mz*R*sin(x1 - x6)*sin(x2)*sin(x7)*sin(x5)*cos(x2) + 8*l**2*x3*sin(x1)*sin(x2)*cos(x1 - x6)*cos(x7)*cos(x5) - 4*l**2*x3*sin(x1)*sin(x7)*cos(x2)*cos(x5) - 4*l**2*x3*sin(x2)*sin(x6)*cos(x7)*cos(x5) + 4*l**2*sin(x1 - x6)*sin(x1)*sin(x2)**2*cos(x7)*cos(x5) - 4*l**2*sin(x2)**2*cos(x6)*cos(x7)*cos(x5) + 4*l**2*sin(x2)*sin(x7)*cos(x1)*cos(x2)*cos(x5) + 2*r**2*x3*sin(x1)*sin(x2)*cos(x1 - x6)*cos(x7)*cos(x5) - r**2*x3*sin(x1)*sin(x7)*cos(x2)*cos(x5) - r**2*x3*sin(x2)*sin(x6)*cos(x7)*cos(x5) + r**2*sin(x1 - x6)*sin(x1)*sin(x2)**2*cos(x7)*cos(x5) - r**2*sin(x2)**2*cos(x6)*cos(x7)*cos(x5) + r**2*sin(x2)*sin(x7)*cos(x1)*cos(x2)*cos(x5))*sin(x7)*diff(y, t)*diff(x3, t)", "Derivative(y(t), t)*Derivative(\u03c8(t), t)": "0", "Derivative(\u03b1(t), t)*Derivative(\u03b2(t), t)": "32*m*(-4*C_mz**2*R*x3**2*sin(x1)*sin(x2)**2*sin(x7)*sin(x5)*cos(x1 - x6) - 4*C_mz**2*R*x3**2*sin(x1)*sin(x2)*sin(x5)*cos(x2)*cos(x7) + 4*C_mz**2*R*x3**2*sin(x1)*sin(x7)*sin(x5)*cos(x1 - x6) + 4*C_mz**2*R*x3*x8*sin(x1)*sin(x2)**3*sin(x5)*cos(x1 - x6) - 4*C_mz**2*R*x3*x8*sin(x1)*sin(x2)*sin(x5)*cos(x1 - x6) - 4*C_mz**2*R*x3*x8*sin(x2)**3*sin(x6)*sin(x5) + 4*C_mz**2*R*x3*x8*sin(x2)*sin(x6)*sin(x5) - 4*C_mz**2*R*x3*sin(x1 - x6)*sin(x1)*sin(x2)**3*sin(x7)*sin(x5) + 12*C_mz**2*R*x3*sin(x1 - x6)*sin(x1)*sin(x2)*sin(x7)*sin(x5) - 4*C_mz**2*R*x3*sin(x1)*sin(x2)**2*cos(x7)*cos(x5) + 4*C_mz**2*R*x3*sin(x1)*sin(x2)*sin(x7)*cos(x1 - x6)*cos(x2)*cos(x5) + 4*C_mz**2*R*x3*sin(x2)**3*sin(x7)*sin(x5)*cos(x6) + 4*C_mz**2*R*x3*sin(x2)**2*sin(x5)*cos(x1)*cos(x2)*cos(x7) - 8*C_mz**2*R*x3*sin(x2)*sin(x7)*sin(x5)*cos(x6) - 4*C_mz**2*R*x8*sin(x1)*sin(x2)**2*cos(x1 - x6)*cos(x2)*cos(x5) + 4*C_mz**2*R*x8*sin(x2)**2*sin(x6)*cos(x2)*cos(x5) + 4*C_mz**2*R*x8*sin(x2)**2*sin(x5)*cos(x1 - x6)*cos(x1) + 4*C_mz**2*R*sin(x1 - x6)*sin(x1)*sin(x2)**2*sin(x7)*cos(x2)*cos(x5) - 4*C_mz**2*R*sin(x1 - x6)*sin(x2)**2*sin(x7)*sin(x5)*cos(x1) + 4*C_mz**2*R*sin(x2)**3*cos(x1)*cos(x7)*cos(x5) - 4*C_mz**2*R*sin(x2)**2*sin(x7)*cos(x2)*cos(x6)*cos(x5) - 4*R*l**2*x3**2*sin(x1)*sin(x2)**2*sin(x7)*sin(x5)*cos(x1 - x6) - 4*R*l**2*x3**2*sin(x1)*sin(x2)*sin(x5)*cos(x2)*cos(x7) + 4*R*l**2*x3**2*sin(x1)*sin(x7)*sin(x5)*cos(x1 - x6) + 4*R*l**2*x3*x8*sin(x1)*sin(x2)**3*sin(x5)*cos(x1 - x6) - 4*R*l**2*x3*x8*sin(x1)*sin(x2)*sin(x5)*cos(x1 - x6) - 4*R*l**2*x3*x8*sin(x2)**3*sin(x6)*sin(x5) + 4*R*l**2*x3*x8*sin(x2)*sin(x6)*sin(x5) - 4*R*l**2*x3*sin(x1 - x6)*sin(x1)*sin(x2)**3*sin(x7)*sin(x5) + 12*R*l**2*x3*sin(x1 - x6)*sin(x1)*sin(x2)*sin(x7)*sin(x5) - 4*R*l**2*x3*sin(x1)*sin(x2)**2*cos(x7)*cos(x5) + 4*R*l**2*x3*sin(x1)*sin(x2)*sin(x7)*cos(x1 - x6)*cos(x2)*cos(x5) + 4*R*l**2*x3*sin(x2)**3*sin(x7)*sin(x5)*cos(x6) + 4*R*l**2*x3*sin(x2)**2*sin(x5)*cos(x1)*cos(x2)*cos(x7) - 8*R*l**2*x3*sin(x2)*sin(x7)*sin(x5)*cos(x6) - 4*R*l**2*x8*sin(x1)*sin(x2)**2*cos(x1 - x6)*cos(x2)*cos(x5) + 4*R*l**2*x8*sin(x2)**2*sin(x6)*cos(x2)*cos(x5) + 4*R*l**2*x8*sin(x2)**2*sin(x5)*cos(x1 - x6)*cos(x1) + 4*R*l**2*sin(x1 - x6)*sin(x1)*sin(x2)**2*sin(x7)*cos(x2)*cos(x5) - 4*R*l**2*sin(x1 - x6)*sin(x2)**2*sin(x7)*sin(x5)*cos(x1) + 4*R*l**2*sin(x2)**3*cos(x1)*cos(x7)*cos(x5) - 4*R*l**2*sin(x2)**2*sin(x7)*cos(x2)*cos(x6)*cos(x5) - R*r**2*x3**2*sin(x1)*sin(x2)**2*sin(x7)*sin(x5)*cos(x1 - x6) - R*r**2*x3**2*sin(x1)*sin(x2)*sin(x5)*cos(x2)*cos(x7) + R*r**2*x3**2*sin(x1)*sin(x7)*sin(x5)*cos(x1 - x6) + R*r**2*x3*x8*sin(x1)*sin(x2)**3*sin(x5)*cos(x1 - x6) - R*r**2*x3*x8*sin(x1)*sin(x2)*sin(x5)*cos(x1 - x6) - R*r**2*x3*x8*sin(x2)**3*sin(x6)*sin(x5) + R*r**2*x3*x8*sin(x2)*sin(x6)*sin(x5) - R*r**2*x3*sin(x1 - x6)*sin(x1)*sin(x2)**3*sin(x7)*sin(x5) + 3*R*r**2*x3*sin(x1 - x6)*sin(x1)*sin(x2)*sin(x7)*sin(x5) - R*r**2*x3*sin(x1)*sin(x2)**2*cos(x7)*cos(x5) + R*r**2*x3*sin(x1)*sin(x2)*sin(x7)*cos(x1 - x6)*cos(x2)*cos(x5) + R*r**2*x3*sin(x2)**3*sin(x7)*sin(x5)*cos(x6) + R*r**2*x3*sin(x2)**2*sin(x5)*cos(x1)*cos(x2)*cos(x7) - 2*R*r**2*x3*sin(x2)*sin(x7)*sin(x5)*cos(x6) - R*r**2*x8*sin(x1)*sin(x2)**2*cos(x1 - x6)*cos(x2)*cos(x5) + R*r**2*x8*sin(x2)**2*sin(x6)*cos(x2)*cos(x5) + R*r**2*x8*sin(x2)**2*sin(x5)*cos(x1 - x6)*cos(x1) + R*r**2*sin(x1 - x6)*sin(x1)*sin(x2)**2*sin(x7)*cos(x2)*cos(x5) - R*r**2*sin(x1 - x6)*sin(x2)**2*sin(x7)*sin(x5)*cos(x1) + R*r**2*sin(x2)**3*cos(x1)*cos(x7)*cos(x5) - R*r**2*sin(x2)**2*sin(x7)*cos(x2)*cos(x6)*cos(x5) - 2*r**3*x3*sin(x1 - x6)*sin(x1)*sin(x2)**2*sin(x7)*sin(x5)*cos(x2) - 2*r**3*x3*sin(x1)*sin(x2)**2*sin(x7)*cos(x1 - x6)*cos(x5) - 2*r**3*x3*sin(x1)*sin(x2)*cos(x2)*cos(x7)*cos(x5) + 2*r**3*x3*sin(x1)*sin(x7)*cos(x1 - x6)*cos(x5) - 2*r**3*x3*sin(x2)**3*sin(x5)*cos(x1)*cos(x7) + 2*r**3*x3*sin(x2)**2*sin(x7)*sin(x5)*cos(x2)*cos(x6) + 2*r**3*x3*sin(x2)*sin(x5)*cos(x1)*cos(x7) + 2*r**3*x3*sin(x7)*sin(x5)*cos(x1 - x6)*cos(x1)*cos(x2) - 2*r**3*x3*sin(x7)*sin(x5)*cos(x2)*cos(x6) + 2*r**3*x8*sin(x1)*sin(x2)**3*cos(x1 - x6)*cos(x5) - 2*r**3*x8*sin(x1)*sin(x2)*cos(x1 - x6)*cos(x5) - 2*r**3*x8*sin(x2)**3*sin(x6)*cos(x5) + 2*r**3*x8*sin(x2)*sin(x6)*cos(x5) - 2*r**3*x8*sin(x2)*sin(x5)*cos(x1 - x6)*cos(x1)*cos(x2) - 2*r**3*sin(x1 - x6)*sin(x1)*sin(x2)**3*sin(x7)*cos(x5) + 2*r**3*sin(x1 - x6)*sin(x1)*sin(x2)*sin(x7)*cos(x5) + 2*r**3*sin(x1 - x6)*sin(x2)*sin(x7)*sin(x5)*cos(x1)*cos(x2) + 2*r**3*sin(x2)**3*sin(x7)*cos(x6)*cos(x5) + 2*r**3*sin(x2)**2*cos(x1)*cos(x2)*cos(x7)*cos(x5) - 2*r**3*sin(x2)*sin(x7)*cos(x6)*cos(x5))*sin(x7)*diff(x1, t)*diff(x2, t)", "Derivative(\u03b1(t), t)*Derivative(\u03b3(t), t)": "32*m*(-4*C_mz**2*R*x3**2*sin(x1 - x6)*sin(x1)*sin(x2)**2*sin(x7)*sin(x5)*cos(x2) - 4*C_mz**2*R*x3**2*sin(x2)**3*sin(x5)*cos(x1)*cos(x7) + 4*C_mz**2*R*x3**2*sin(x2)**2*sin(x7)*sin(x5)*cos(x2)*cos(x6) + 4*C_mz**2*R*x3**2*sin(x2)*sin(x5)*cos(x1)*cos(x7) + 4*C_mz**2*R*x3**2*sin(x7)*sin(x5)*cos(x1 - x6)*cos(x1)*cos(x2) - 4*C_mz**2*R*x3**2*sin(x7)*sin(x5)*cos(x2)*cos(x6) - 4*C_mz**2*R*x3*x8*sin(x2)*sin(x5)*cos(x1 - x6)*cos(x1)*cos(x2) - 4*C_mz**2*R*x3*sin(x1 - x6)*sin(x1)*sin(x2)**3*sin(x7)*cos(x5) + 4*C_mz**2*R*x3*sin(x1 - x6)*sin(x2)*sin(x7)*sin(x5)*cos(x1)*cos(x2) - 12*C_mz**2*R*x3*sin(x1)**2*sin(x2)*sin(x7)*cos(x6)*cos(x5) + 12*C_mz**2*R*x3*sin(x1)*sin(x2)*sin(x6)*sin(x7)*cos(x1)*cos(x5) + 4*C_mz**2*R*x3*sin(x2)**3*sin(x7)*cos(x6)*cos(x5) + 4*C_mz**2*R*x3*sin(x2)**2*cos(x1)*cos(x2)*cos(x7)*cos(x5) + 4*C_mz**2*R*x3*sin(x2)*sin(x7)*cos(x6)*cos(x5) - 8*C_mz**2*R*x8*sin(x2)**2*cos(x1 - x6)*cos(x1)*cos(x5) + 8*C_mz**2*R*sin(x1 - x6)*sin(x2)**2*sin(x7)*cos(x1)*cos(x5) - 4*R*l**2*x3**2*sin(x1 - x6)*sin(x1)*sin(x2)**2*sin(x7)*sin(x5)*cos(x2) - 4*R*l**2*x3**2*sin(x2)**3*sin(x5)*cos(x1)*cos(x7) + 4*R*l**2*x3**2*sin(x2)**2*sin(x7)*sin(x5)*cos(x2)*cos(x6) + 4*R*l**2*x3**2*sin(x2)*sin(x5)*cos(x1)*cos(x7) + 4*R*l**2*x3**2*sin(x7)*sin(x5)*cos(x1 - x6)*cos(x1)*cos(x2) - 4*R*l**2*x3**2*sin(x7)*sin(x5)*cos(x2)*cos(x6) - 4*R*l**2*x3*x8*sin(x2)*sin(x5)*cos(x1 - x6)*cos(x1)*cos(x2) - 4*R*l**2*x3*sin(x1 - x6)*sin(x1)*sin(x2)**3*sin(x7)*cos(x5) + 4*R*l**2*x3*sin(x1 - x6)*sin(x2)*sin(x7)*sin(x5)*cos(x1)*cos(x2) - 12*R*l**2*x3*sin(x1)**2*sin(x2)*sin(x7)*cos(x6)*cos(x5) + 12*R*l**2*x3*sin(x1)*sin(x2)*sin(x6)*sin(x7)*cos(x1)*cos(x5) + 4*R*l**2*x3*sin(x2)**3*sin(x7)*cos(x6)*cos(x5) + 4*R*l**2*x3*sin(x2)**2*cos(x1)*cos(x2)*cos(x7)*cos(x5) + 4*R*l**2*x3*sin(x2)*sin(x7)*cos(x6)*cos(x5) - 8*R*l**2*x8*sin(x2)**2*cos(x1 - x6)*cos(x1)*cos(x5) + 8*R*l**2*sin(x1 - x6)*sin(x2)**2*sin(x7)*cos(x1)*cos(x5) - R*r**2*x3**2*sin(x1 - x6)*sin(x1)*sin(x2)**2*sin(x7)*sin(x5)*cos(x2) - R*r**2*x3**2*sin(x2)**3*sin(x5)*cos(x1)*cos(x7) + R*r**2*x3**2*sin(x2)**2*sin(x7)*sin(x5)*cos(x2)*cos(x6) + R*r**2*x3**2*sin(x2)*sin(x5)*cos(x1)*cos(x7) + R*r**2*x3**2*sin(x7)*sin(x5)*cos(x1 - x6)*cos(x1)*cos(x2) - R*r**2*x3**2*sin(x7)*sin(x5)*cos(x2)*cos(x6) - R*r**2*x3*x8*sin(x2)*sin(x5)*cos(x1 - x6)*cos(x1)*cos(x2) - R*r**2*x3*sin(x1 - x6)*sin(x1)*sin(x2)**3*sin(x7)*cos(x5) + R*r**2*x3*sin(x1 - x6)*sin(x2)*sin(x7)*sin(x5)*cos(x1)*cos(x2) - 3*R*r**2*x3*sin(x1)**2*sin(x2)*sin(x7)*cos(x6)*cos(x5) + 3*R*r**2*x3*sin(x1)*sin(x2)*sin(x6)*sin(x7)*cos(x1)*cos(x5) + R*r**2*x3*sin(x2)**3*sin(x7)*cos(x6)*cos(x5) + R*r**2*x3*sin(x2)**2*cos(x1)*cos(x2)*cos(x7)*cos(x5) + R*r**2*x3*sin(x2)*sin(x7)*cos(x6)*cos(x5) - 2*R*r**2*x8*sin(x2)**2*cos(x1 - x6)*cos(x1)*cos(x5) + 2*R*r**2*sin(x1 - x6)*sin(x2)**2*sin(x7)*cos(x1)*cos(x5) + 2*r**3*x3**2*sin(x1 - x6)*sin(x1)*sin(x2)**3*sin(x7)*sin(x5) + 2*r**3*x3**2*sin(x1)*sin(x2)**2*cos(x7)*cos(x5) - 2*r**3*x3**2*sin(x1)*sin(x2)*sin(x7)*cos(x1 - x6)*cos(x2)*cos(x5) - 2*r**3*x3**2*sin(x2)**3*sin(x7)*sin(x5)*cos(x6) - 2*r**3*x3**2*sin(x2)**2*sin(x5)*cos(x1)*cos(x2)*cos(x7) - 2*r**3*x3**2*sin(x2)*sin(x7)*sin(x5)*cos(x1 - x6)*cos(x1) + 2*r**3*x3**2*sin(x2)*sin(x7)*sin(x5)*cos(x6) + 2*r**3*x3*x8*sin(x1)*sin(x2)**2*cos(x1 - x6)*cos(x2)*cos(x5) - 2*r**3*x3*x8*sin(x2)**2*sin(x6)*cos(x2)*cos(x5) + 2*r**3*x3*x8*sin(x2)**2*sin(x5)*cos(x1 - x6)*cos(x1) - 2*r**3*x3*sin(x1 - x6)*sin(x1)*sin(x2)**2*sin(x7)*cos(x2)*cos(x5) - 2*r**3*x3*sin(x1 - x6)*sin(x2)**2*sin(x7)*sin(x5)*cos(x1) - 2*r**3*x3*sin(x2)**3*cos(x1)*cos(x7)*cos(x5) + 2*r**3*x3*sin(x2)**2*sin(x7)*cos(x2)*cos(x6)*cos(x5))*sin(x7)*diff(x1, t)*diff(x3, t)", "Derivative(\u03b1(t), t)*Derivative(\u03c8(t), t)": "0", "Derivative(\u03b2(t), t)*Derivative(\u03b3(t), t)": "32*m*(4*C_mz**2*R*x3*sin(x1 - x6)*sin(x1)*sin(x2)**2*sin(x7)*sin(x5) - 4*C_mz**2*R*x3*sin(x1)*sin(x2)*cos(x7)*cos(x5) + 4*C_mz**2*R*x3*sin(x1)*sin(x7)*cos(x1 - x6)*cos(x2)*cos(x5) - 4*C_mz**2*R*x3*sin(x2)**2*sin(x7)*sin(x5)*cos(x6) - 4*C_mz**2*R*x3*sin(x2)*sin(x5)*cos(x1)*cos(x2)*cos(x7) - 4*C_mz**2*R*x3*sin(x7)*sin(x5)*cos(x1 - x6)*cos(x1) + 4*C_mz**2*R*x3*sin(x7)*sin(x5)*cos(x6) - 4*C_mz**2*R*x8*sin(x1)*sin(x2)*cos(x1 - x6)*cos(x2)*cos(x5) + 4*C_mz**2*R*x8*sin(x2)*sin(x6)*cos(x2)*cos(x5) + 4*C_mz**2*R*x8*sin(x2)*sin(x5)*cos(x1 - x6)*cos(x1) + 4*C_mz**2*R*sin(x1 - x6)*sin(x1)*sin(x2)*sin(x7)*cos(x2)*cos(x5) - 4*C_mz**2*R*sin(x1 - x6)*sin(x2)*sin(x7)*sin(x5)*cos(x1) + 4*C_mz**2*R*sin(x2)**2*cos(x1)*cos(x7)*cos(x5) - 4*C_mz**2*R*sin(x2)*sin(x7)*cos(x2)*cos(x6)*cos(x5) + 4*R*l**2*x3*sin(x1 - x6)*sin(x1)*sin(x2)**2*sin(x7)*sin(x5) - 4*R*l**2*x3*sin(x1)*sin(x2)*cos(x7)*cos(x5) + 4*R*l**2*x3*sin(x1)*sin(x7)*cos(x1 - x6)*cos(x2)*cos(x5) - 4*R*l**2*x3*sin(x2)**2*sin(x7)*sin(x5)*cos(x6) - 4*R*l**2*x3*sin(x2)*sin(x5)*cos(x1)*cos(x2)*cos(x7) - 4*R*l**2*x3*sin(x7)*sin(x5)*cos(x1 - x6)*cos(x1) + 4*R*l**2*x3*sin(x7)*sin(x5)*cos(x6) - 4*R*l**2*x8*sin(x1)*sin(x2)*cos(x1 - x6)*cos(x2)*cos(x5) + 4*R*l**2*x8*sin(x2)*sin(x6)*cos(x2)*cos(x5) + 4*R*l**2*x8*sin(x2)*sin(x5)*cos(x1 - x6)*cos(x1) + 4*R*l**2*sin(x1 - x6)*sin(x1)*sin(x2)*sin(x7)*cos(x2)*cos(x5) - 4*R*l**2*sin(x1 - x6)*sin(x2)*sin(x7)*sin(x5)*cos(x1) + 4*R*l**2*sin(x2)**2*cos(x1)*cos(x7)*cos(x5) - 4*R*l**2*sin(x2)*sin(x7)*cos(x2)*cos(x6)*cos(x5) + R*r**2*x3*sin(x1 - x6)*sin(x1)*sin(x2)**2*sin(x7)*sin(x5) - R*r**2*x3*sin(x1)*sin(x2)*cos(x7)*cos(x5) + R*r**2*x3*sin(x1)*sin(x7)*cos(x1 - x6)*cos(x2)*cos(x5) - R*r**2*x3*sin(x2)**2*sin(x7)*sin(x5)*cos(x6) - R*r**2*x3*sin(x2)*sin(x5)*cos(x1)*cos(x2)*cos(x7) - R*r**2*x3*sin(x7)*sin(x5)*cos(x1 - x6)*cos(x1) + R*r**2*x3*sin(x7)*sin(x5)*cos(x6) - R*r**2*x8*sin(x1)*sin(x2)*cos(x1 - x6)*cos(x2)*cos(x5) + R*r**2*x8*sin(x2)*sin(x6)*cos(x2)*cos(x5) + R*r**2*x8*sin(x2)*sin(x5)*cos(x1 - x6)*cos(x1) + R*r**2*sin(x1 - x6)*sin(x1)*sin(x2)*sin(x7)*cos(x2)*cos(x5) - R*r**2*sin(x1 - x6)*sin(x2)*sin(x7)*sin(x5)*cos(x1) + R*r**2*sin(x2)**2*cos(x1)*cos(x7)*cos(x5) - R*r**2*sin(x2)*sin(x7)*cos(x2)*cos(x6)*cos(x5) - 2*r**3*x3*sin(x1 - x6)*sin(x1)*sin(x2)**2*sin(x7)*sin(x5) - 2*r**3*x3*sin(x1)*sin(x2)*cos(x7)*cos(x5) + 2*r**3*x3*sin(x1)*sin(x7)*cos(x1 - x6)*cos(x2)*cos(x5) + 2*r**3*x3*sin(x2)**2*sin(x7)*sin(x5)*cos(x6) + 2*r**3*x3*sin(x2)*sin(x5)*cos(x1)*cos(x2)*cos(x7) + 2*r**3*x3*sin(x7)*sin(x5)*cos(x1 - x6)*cos(x1) - 2*r**3*x3*sin(x7)*sin(x5)*cos(x6) - 2*r**3*x8*sin(x1)*sin(x2)*cos(x1 - x6)*cos(x2)*cos(x5) + 2*r**3*x8*sin(x2)*sin(x6)*cos(x2)*cos(x5) - 2*r**3*x8*sin(x2)*sin(x5)*cos(x1 - x6)*cos(x1) + 2*r**3*sin(x1 - x6)*sin(x1)*sin(x2)*sin(x7)*cos(x2)*cos(x5) + 2*r**3*sin(x1 - x6)*sin(x2)*sin(x7)*sin(x5)*cos(x1) + 2*r**3*sin(x2)**2*cos(x1)*cos(x7)*cos(x5) - 2*r**3*sin(x2)*sin(x7)*cos(x2)*cos(x6)*cos(x5))*sin(x7)*diff(x2, t)*diff(x3, t)", "Derivative(\u03b2(t), t)*Derivative(\u03c8(t), t)": "0", "Derivative(\u03b3(t), t)*Derivative(\u03c8(t), t)": "0", "Derivative(x(t), t)**2": "128*C_mz*m*(-2*x3**2*sin(x1 - x6)*sin(x1)**2*sin(x2)*cos(x5) + x3**2*sin(x1)*sin(x2)*cos(x6)*cos(x5) + x3*x8*sin(x1 - x6)*sin(x1)**2*sin(x2)**2*sin(x7)*cos(x5) - x3*x8*sin(x1)*sin(x2)**2*sin(x7)*cos(x6)*cos(x5) - x3*x8*sin(x1)*sin(x2)*cos(x1)*cos(x2)*cos(x7)*cos(x5) - 2*x3*sin(x1 - x6)*sin(x1)**2*sin(x5)*cos(x2) + 2*x3*sin(x1 - x6)*sin(x1)*cos(x1)*cos(x5) + x3*sin(x1)**2*sin(x2)**2*cos(x1 - x6)*cos(x5) - x3*sin(x1)*sin(x2)**2*sin(x6)*cos(x5) + x3*sin(x1)*sin(x5)*cos(x2)*cos(x6) - x3*cos(x1)*cos(x6)*cos(x5) + x8*sin(x1 - x6)*sin(x1)**2*sin(x2)*sin(x7)*sin(x5)*cos(x2) - x8*sin(x1 - x6)*sin(x1)*sin(x2)*sin(x7)*cos(x1)*cos(x5) - x8*sin(x1)*sin(x2)*sin(x7)*sin(x5)*cos(x2)*cos(x6) - x8*sin(x1)*sin(x5)*cos(x1)*cos(x2)**2*cos(x7) + x8*sin(x2)*sin(x7)*cos(x1)*cos(x6)*cos(x5) + x8*cos(x1)**2*cos(x2)*cos(x7)*cos(x5) + sin(x1)**2*sin(x2)*sin(x5)*cos(x1 - x6)*cos(x2) - sin(x1)*sin(x2)*sin(x6)*sin(x5)*cos(x2) - sin(x1)*sin(x2)*cos(x1 - x6)*cos(x1)*cos(x5) + sin(x2)*sin(x6)*cos(x1)*cos(x5))*sin(x2)*sin(x7)*diff(x, t)**2", "Derivative(y(t), t)**2": "128*C_mz*m*(2*x3**2*sin(x1)*sin(x2)**2*cos(x1 - x6)*cos(x1)*cos(x7)*cos(x5) - x3**2*sin(x1)*sin(x2)*sin(x7)*cos(x1)*cos(x2)*cos(x5) - x3**2*sin(x2)**2*sin(x6)*cos(x1)*cos(x7)*cos(x5) + x3*sin(x1 - x6)*sin(x1)*sin(x2)**3*cos(x1)*cos(x7)*cos(x5) + 2*x3*sin(x1)**2*sin(x2)*cos(x1 - x6)*cos(x7)*cos(x5) - x3*sin(x1)**2*sin(x7)*cos(x2)*cos(x5) - x3*sin(x1)*sin(x2)*sin(x6)*cos(x7)*cos(x5) + 2*x3*sin(x1)*sin(x2)*sin(x5)*cos(x1 - x6)*cos(x1)*cos(x2)*cos(x7) - x3*sin(x1)*sin(x7)*sin(x5)*cos(x1)*cos(x2)**2 - x3*sin(x2)**3*cos(x1)*cos(x6)*cos(x7)*cos(x5) + x3*sin(x2)**2*sin(x7)*cos(x1)**2*cos(x2)*cos(x5) - x3*sin(x2)*sin(x6)*sin(x5)*cos(x1)*cos(x2)*cos(x7) + sin(x1 - x6)*sin(x1)**2*sin(x2)**2*cos(x7)*cos(x5) + sin(x1 - x6)*sin(x1)*sin(x2)**2*sin(x5)*cos(x1)*cos(x2)*cos(x7) - sin(x1)*sin(x2)**2*cos(x6)*cos(x7)*cos(x5) + sin(x1)*sin(x2)*sin(x7)*cos(x1)*cos(x2)*cos(x5) - sin(x2)**2*sin(x5)*cos(x1)*cos(x2)*cos(x6)*cos(x7) + sin(x2)*sin(x7)*sin(x5)*cos(x1)**2*cos(x2)**2)*sin(x7)*diff(y, t)**2", "Derivative(\u03b1(t), t)**2": "32*R*m*(-8*C_mz**2*x3**2*sin(x1 - x6)*sin(x1)*sin(x7)*sin(x5)*cos(x2) + 4*C_mz**2*x3**2*sin(x7)*sin(x5)*cos(x2)*cos(x6) - 4*C_mz**2*x3*x8*sin(x2)*sin(x5)*cos(x1 - x6)*cos(x1)*cos(x2) - 8*C_mz**2*x3*sin(x1 - x6)*sin(x1)*sin(x2)*sin(x7)*cos(x5) + 4*C_mz**2*x3*sin(x1 - x6)*sin(x2)*sin(x7)*sin(x5)*cos(x1)*cos(x2) + 4*C_mz**2*x3*sin(x2)*sin(x7)*cos(x6)*cos(x5) - 4*C_mz**2*x8*sin(x2)**2*cos(x1 - x6)*cos(x1)*cos(x5) + 4*C_mz**2*sin(x1 - x6)*sin(x2)**2*sin(x7)*cos(x1)*cos(x5) - 8*l**2*x3**2*sin(x1 - x6)*sin(x1)*sin(x7)*sin(x5)*cos(x2) + 4*l**2*x3**2*sin(x7)*sin(x5)*cos(x2)*cos(x6) - 4*l**2*x3*x8*sin(x2)*sin(x5)*cos(x1 - x6)*cos(x1)*cos(x2) - 8*l**2*x3*sin(x1 - x6)*sin(x1)*sin(x2)*sin(x7)*cos(x5) + 4*l**2*x3*sin(x1 - x6)*sin(x2)*sin(x7)*sin(x5)*cos(x1)*cos(x2) + 4*l**2*x3*sin(x2)*sin(x7)*cos(x6)*cos(x5) - 4*l**2*x8*sin(x2)**2*cos(x1 - x6)*cos(x1)*cos(x5) + 4*l**2*sin(x1 - x6)*sin(x2)**2*sin(x7)*cos(x1)*cos(x5) - 2*r**2*x3**2*sin(x1 - x6)*sin(x1)*sin(x7)*sin(x5)*cos(x2) + r**2*x3**2*sin(x7)*sin(x5)*cos(x2)*cos(x6) - r**2*x3*x8*sin(x2)*sin(x5)*cos(x1 - x6)*cos(x1)*cos(x2) - 2*r**2*x3*sin(x1 - x6)*sin(x1)*sin(x2)*sin(x7)*cos(x5) + r**2*x3*sin(x1 - x6)*sin(x2)*sin(x7)*sin(x5)*cos(x1)*cos(x2) + r**2*x3*sin(x2)*sin(x7)*cos(x6)*cos(x5) - r**2*x8*sin(x2)**2*cos(x1 - x6)*cos(x1)*cos(x5) + r**2*sin(x1 - x6)*sin(x2)**2*sin(x7)*cos(x1)*cos(x5))*sin(x2)*sin(x7)*diff(x1, t)**2", "Derivative(\u03b2(t), t)**2": "32*R*m*(4*C_mz**2*x3*sin(x1)*sin(x2)*cos(x7) - 4*C_mz**2*x3*sin(x1)*sin(x7)*cos(x1 - x6)*cos(x2) + 4*C_mz**2*x8*sin(x1)*sin(x2)*cos(x1 - x6)*cos(x2) - 4*C_mz**2*x8*sin(x2)*sin(x6)*cos(x2) - 4*C_mz**2*sin(x1 - x6)*sin(x1)*sin(x2)*sin(x7)*cos(x2) - 4*C_mz**2*sin(x2)**2*cos(x1)*cos(x7) + 4*C_mz**2*sin(x2)*sin(x7)*cos(x2)*cos(x6) + 4*l**2*x3*sin(x1)*sin(x2)*cos(x7) - 4*l**2*x3*sin(x1)*sin(x7)*cos(x1 - x6)*cos(x2) + 4*l**2*x8*sin(x1)*sin(x2)*cos(x1 - x6)*cos(x2) - 4*l**2*x8*sin(x2)*sin(x6)*cos(x2) - 4*l**2*sin(x1 - x6)*sin(x1)*sin(x2)*sin(x7)*cos(x2) - 4*l**2*sin(x2)**2*cos(x1)*cos(x7) + 4*l**2*sin(x2)*sin(x7)*cos(x2)*cos(x6) + r**2*x3*sin(x1)*sin(x2)*cos(x7) - r**2*x3*sin(x1)*sin(x7)*cos(x1 - x6)*cos(x2) + r**2*x8*sin(x1)*sin(x2)*cos(x1 - x6)*cos(x2) - r**2*x8*sin(x2)*sin(x6)*cos(x2) - r**2*sin(x1 - x6)*sin(x1)*sin(x2)*sin(x7)*cos(x2) - r**2*sin(x2)**2*cos(x1)*cos(x7) + r**2*sin(x2)*sin(x7)*cos(x2)*cos(x6))*sin(x7)*sin(x5)*diff(x2, t)**2", "Derivative(\u03b3(t), t)**2": "32*R*m*(-4*C_mz**2*x3*sin(x1 - x6)*sin(x1)*sin(x2)**2*sin(x7) + 4*C_mz**2*x3*sin(x2)**2*sin(x7)*cos(x6) + 4*C_mz**2*x3*sin(x2)*cos(x1)*cos(x2)*cos(x7) + 4*C_mz**2*x3*sin(x7)*cos(x1 - x6)*cos(x1) - 4*C_mz**2*x3*sin(x7)*cos(x6) - 4*C_mz**2*x8*sin(x2)*cos(x1 - x6)*cos(x1) + 4*C_mz**2*sin(x1 - x6)*sin(x2)*sin(x7)*cos(x1) - 4*l**2*x3*sin(x1 - x6)*sin(x1)*sin(x2)**2*sin(x7) + 4*l**2*x3*sin(x2)**2*sin(x7)*cos(x6) + 4*l**2*x3*sin(x2)*cos(x1)*cos(x2)*cos(x7) + 4*l**2*x3*sin(x7)*cos(x1 - x6)*cos(x1) - 4*l**2*x3*sin(x7)*cos(x6) - 4*l**2*x8*sin(x2)*cos(x1 - x6)*cos(x1) + 4*l**2*sin(x1 - x6)*sin(x2)*sin(x7)*cos(x1) - r**2*x3*sin(x1 - x6)*sin(x1)*sin(x2)**2*sin(x7) + r**2*x3*sin(x2)**2*sin(x7)*cos(x6) + r**2*x3*sin(x2)*cos(x1)*cos(x2)*cos(x7) + r**2*x3*sin(x7)*cos(x1 - x6)*cos(x1) - r**2*x3*sin(x7)*cos(x6) - r**2*x8*sin(x2)*cos(x1 - x6)*cos(x1) + r**2*sin(x1 - x6)*sin(x2)*sin(x7)*cos(x1))*sin(x7)*cos(x5)*diff(x3, t)**2", "Derivative(\u03c8(t), t)**2": "0", "free": "128*M_\u03c8*r*x3*sin(x1 - x6)*sin(x1)*sin(x2)**2*sin(x7)**2*sin(x5) + 128*M_\u03c8*r*x3*sin(x1)*sin(x2)*sin(x7)*cos(x7)*cos(x5) - 128*M_\u03c8*r*x3*sin(x1)*sin(x7)**2*cos(x1 - x6)*cos(x2)*cos(x5) - 128*M_\u03c8*r*x3*sin(x2)**2*sin(x7)**2*sin(x5)*cos(x6) - 128*M_\u03c8*r*x3*sin(x2)*sin(x7)*sin(x5)*cos(x1)*cos(x2)*cos(x7) - 128*M_\u03c8*r*x3*sin(x7)**2*sin(x5)*cos(x1 - x6)*cos(x1) + 128*M_\u03c8*r*x3*sin(x7)**2*sin(x5)*cos(x6) + 128*M_\u03c8*r*x8*sin(x1)*sin(x2)*sin(x7)*cos(x1 - x6)*cos(x2)*cos(x5) - 128*M_\u03c8*r*x8*sin(x2)*sin(x6)*sin(x7)*cos(x2)*cos(x5) + 128*M_\u03c8*r*x8*sin(x2)*sin(x7)*sin(x5)*cos(x1 - x6)*cos(x1) - 128*M_\u03c8*r*sin(x1 - x6)*sin(x1)*sin(x2)*sin(x7)**2*cos(x2)*cos(x5) - 128*M_\u03c8*r*sin(x1 - x6)*sin(x2)*sin(x7)**2*sin(x5)*cos(x1) - 128*M_\u03c8*r*sin(x2)**2*sin(x7)*cos(x1)*cos(x7)*cos(x5) + 128*M_\u03c8*r*sin(x2)*sin(x7)**2*cos(x2)*cos(x6)*cos(x5)"}