{"0": "-4478976*J_pz*r**2*x2**4*sin(x7)**12*sin(x5)*cos(x6)**9*cos(x7)*cos(x5)**8*diff(y, t)**2", "1": "-4478976*J_pz*r**2*x2**4*sin(x6)**8*sin(x7)**12*sin(x5)**9*cos(x6)*cos(x7)*diff(y, t)**2", "2": "-4478976*J_pz*r**2*x2**4*sin(x7)**13*cos(x6)**9*cos(x7)*cos(x5)**9*diff(x, t)*diff(y, t)", "3": "-4478976*J_pz*r**2*x2**4*sin(x6)**9*sin(x7)**13*sin(x5)**9*cos(x7)*diff(x, t)*diff(y, t)", "4": "4478976*J_pz*r**2*x2**4*sin(x6)*sin(x7)**12*cos(x6)**8*cos(x7)*cos(x5)**9*diff(y, t)**2", "5": "4478976*J_pz*r**2*x2**4*sin(x6)**9*sin(x7)**12*sin(x5)**8*cos(x7)*cos(x5)*diff(y, t)**2", "6": "4478976*J_pz*r**2*x2**4*sin(x7)**12*cos(x6)**9*cos(x7)**2*cos(x5)**9*diff(x, t)*diff(y, t)", "7": "4478976*J_pz*r**2*x2**4*sin(x6)**9*sin(x7)**12*sin(x5)**9*cos(x7)**2*diff(x, t)*diff(y, t)", "8": "-313528320*J_pz*r**2*x2**4*sin(x6)**4*sin(x7)**12*sin(x5)**5*cos(x6)**5*cos(x7)*cos(x5)**4*diff(y, t)**2", "9": "-250822656*J_pz*r**2*x2**4*sin(x6)**5*sin(x7)**12*sin(x5)**6*cos(x6)**4*cos(x7)*cos(x5)**3*diff(y, t)**2", "10": "-250822656*J_pz*r**2*x2**4*sin(x6)**3*sin(x7)**12*sin(x5)**4*cos(x6)**6*cos(x7)*cos(x5)**5*diff(y, t)**2", "11": "-125411328*J_pz*r**2*x2**4*sin(x6)**6*sin(x7)**12*sin(x5)**7*cos(x6)**3*cos(x7)*cos(x5)**2*diff(y, t)**2", "12": "-125411328*J_pz*r**2*x2**4*sin(x6)**2*sin(x7)**12*sin(x5)**3*cos(x6)**7*cos(x7)*cos(x5)**6*diff(y, t)**2", "13": "-35831808*J_pz*r**2*x2**4*sin(x6)**7*sin(x7)**12*sin(x5)**8*cos(x6)**2*cos(x7)*cos(x5)*diff(y, t)**2", "14": "-35831808*J_pz*r**2*x2**4*sin(x6)*sin(x7)**12*sin(x5)**2*cos(x6)**8*cos(x7)*cos(x5)**7*diff(y, t)**2", "15": "-4478976*J_pz*R*r**2*x2**4*sin(x7)**12*cos(x6)**8*cos(x7)*cos(x5)**9*diff(y, t)*diff(x3, t)", "16": "-2985984*M*R**2*r**2*x2**4*sin(x7)**12*sin(x5)*cos(x6)**9*cos(x7)*cos(x5)**8*diff(y, t)**2", "17": "-2985984*M*R**2*r**2*x2**4*sin(x6)**8*sin(x7)**12*sin(x5)**9*cos(x6)*cos(x7)*diff(y, t)**2", "18": "-2985984*M*R**2*r**2*x2**4*sin(x7)**13*cos(x6)**9*cos(x7)*cos(x5)**9*diff(x, t)*diff(y, t)", "19": "-2985984*M*R**2*r**2*x2**4*sin(x6)**9*sin(x7)**13*sin(x5)**9*cos(x7)*diff(x, t)*diff(y, t)", "20": "-2985984*M*R**3*r**2*x2**4*sin(x7)**12*cos(x6)**8*cos(x7)*cos(x5)**9*diff(y, t)*diff(x3, t)", "21": "2985984*M*R**2*r**2*x2**4*sin(x6)*sin(x7)**12*cos(x6)**8*cos(x7)*cos(x5)**9*diff(y, t)**2", "22": "2985984*M*R**2*r**2*x2**4*sin(x6)**9*sin(x7)**12*sin(x5)**8*cos(x7)*cos(x5)*diff(y, t)**2", "23": "2985984*M*R**2*r**2*x2**4*sin(x7)**12*cos(x6)**9*cos(x7)**2*cos(x5)**9*diff(x, t)*diff(y, t)", "24": "2985984*M*R**2*r**2*x2**4*sin(x6)**9*sin(x7)**12*sin(x5)**9*cos(x7)**2*diff(x, t)*diff(y, t)", "25": "2985984*M*R**3*r**2*x2**4*sin(x6)**8*sin(x7)**12*sin(x5)**9*cos(x7)*diff(y, t)*diff(x2, t)", "26": "4478976*J_pz*R*r**2*x2**4*sin(x6)**8*sin(x7)**12*sin(x5)**9*cos(x7)*diff(y, t)*diff(x2, t)", "27": "35831808*J_pz*r**2*x2**4*sin(x6)**2*sin(x7)**12*sin(x5)*cos(x6)**7*cos(x7)*cos(x5)**8*diff(y, t)**2", "28": "35831808*J_pz*r**2*x2**4*sin(x6)**8*sin(x7)**12*sin(x5)**7*cos(x6)*cos(x7)*cos(x5)**2*diff(y, t)**2", "29": "125411328*J_pz*r**2*x2**4*sin(x6)**7*sin(x7)**12*sin(x5)**6*cos(x6)**2*cos(x7)*cos(x5)**3*diff(y, t)**2", "30": "125411328*J_pz*r**2*x2**4*sin(x6)**3*sin(x7)**12*sin(x5)**2*cos(x6)**6*cos(x7)*cos(x5)**7*diff(y, t)**2", "31": "250822656*J_pz*r**2*x2**4*sin(x6)**6*sin(x7)**12*sin(x5)**5*cos(x6)**3*cos(x7)*cos(x5)**4*diff(y, t)**2", "32": "250822656*J_pz*r**2*x2**4*sin(x6)**4*sin(x7)**12*sin(x5)**3*cos(x6)**5*cos(x7)*cos(x5)**6*diff(y, t)**2", "33": "313528320*J_pz*r**2*x2**4*sin(x6)**5*sin(x7)**12*sin(x5)**4*cos(x6)**4*cos(x7)*cos(x5)**5*diff(y, t)**2", "34": "-564350976*J_pz*r**2*x2**4*sin(x6)**5*sin(x7)**13*sin(x5)**5*cos(x6)**4*cos(x7)*cos(x5)**4*diff(x, t)*diff(y, t)", "35": "-564350976*J_pz*r**2*x2**4*sin(x6)**4*sin(x7)**13*sin(x5)**4*cos(x6)**5*cos(x7)*cos(x5)**5*diff(x, t)*diff(y, t)", "36": "-376233984*J_pz*r**2*x2**4*sin(x6)**6*sin(x7)**13*sin(x5)**6*cos(x6)**3*cos(x7)*cos(x5)**3*diff(x, t)*diff(y, t)", "37": "-376233984*J_pz*r**2*x2**4*sin(x6)**3*sin(x7)**13*sin(x5)**3*cos(x6)**6*cos(x7)*cos(x5)**6*diff(x, t)*diff(y, t)", "38": "-209018880*M*R**2*r**2*x2**4*sin(x6)**4*sin(x7)**12*sin(x5)**5*cos(x6)**5*cos(x7)*cos(x5)**4*diff(y, t)**2", "39": "-167215104*M*R**2*r**2*x2**4*sin(x6)**5*sin(x7)**12*sin(x5)**6*cos(x6)**4*cos(x7)*cos(x5)**3*diff(y, t)**2", "40": "-167215104*M*R**2*r**2*x2**4*sin(x6)**3*sin(x7)**12*sin(x5)**4*cos(x6)**6*cos(x7)*cos(x5)**5*diff(y, t)**2", "41": "-161243136*J_pz*r**2*x2**4*sin(x6)**7*sin(x7)**13*sin(x5)**7*cos(x6)**2*cos(x7)*cos(x5)**2*diff(x, t)*diff(y, t)", "42": "-161243136*J_pz*r**2*x2**4*sin(x6)**2*sin(x7)**13*sin(x5)**2*cos(x6)**7*cos(x7)*cos(x5)**7*diff(x, t)*diff(y, t)", "43": "-83607552*M*R**2*r**2*x2**4*sin(x6)**6*sin(x7)**12*sin(x5)**7*cos(x6)**3*cos(x7)*cos(x5)**2*diff(y, t)**2", "44": "-83607552*M*R**2*r**2*x2**4*sin(x6)**2*sin(x7)**12*sin(x5)**3*cos(x6)**7*cos(x7)*cos(x5)**6*diff(y, t)**2", "45": "-40310784*J_pz*r**2*x2**4*sin(x6)*sin(x7)**13*sin(x5)*cos(x6)**8*cos(x7)*cos(x5)**8*diff(x, t)*diff(y, t)", "46": "-40310784*J_pz*r**2*x2**4*sin(x6)**8*sin(x7)**13*sin(x5)**8*cos(x6)*cos(x7)*cos(x5)*diff(x, t)*diff(y, t)", "47": "-23887872*M*R**2*r**2*x2**4*sin(x6)**7*sin(x7)**12*sin(x5)**8*cos(x6)**2*cos(x7)*cos(x5)*diff(y, t)**2", "48": "-23887872*M*R**2*r**2*x2**4*sin(x6)*sin(x7)**12*sin(x5)**2*cos(x6)**8*cos(x7)*cos(x5)**7*diff(y, t)**2", "49": "-4478976*J_pz*R*r**2*x2**4*sin(x6)**8*sin(x7)**12*sin(x5)**8*cos(x7)*cos(x5)*diff(y, t)*diff(x3, t)", "50": "-2985984*M*R**3*r**2*x2**4*sin(x6)**8*sin(x7)**12*sin(x5)**8*cos(x7)*cos(x5)*diff(y, t)*diff(x3, t)", "51": "2985984*M*R**3*r**2*x2**4*sin(x7)**12*sin(x5)*cos(x6)**8*cos(x7)*cos(x5)**8*diff(y, t)*diff(x2, t)", "52": "4478976*J_pz*R*r**2*x2**4*sin(x7)**12*sin(x5)*cos(x6)**8*cos(x7)*cos(x5)**8*diff(y, t)*diff(x2, t)", "53": "23887872*M*R**2*r**2*x2**4*sin(x6)**2*sin(x7)**12*sin(x5)*cos(x6)**7*cos(x7)*cos(x5)**8*diff(y, t)**2", "54": "23887872*M*R**2*r**2*x2**4*sin(x6)**8*sin(x7)**12*sin(x5)**7*cos(x6)*cos(x7)*cos(x5)**2*diff(y, t)**2", "55": "40310784*J_pz*r**2*x2**4*sin(x6)*sin(x7)**12*sin(x5)*cos(x6)**8*cos(x7)**2*cos(x5)**8*diff(x, t)*diff(y, t)", "56": "40310784*J_pz*r**2*x2**4*sin(x6)**8*sin(x7)**12*sin(x5)**8*cos(x6)*cos(x7)**2*cos(x5)*diff(x, t)*diff(y, t)", "57": "83607552*M*R**2*r**2*x2**4*sin(x6)**7*sin(x7)**12*sin(x5)**6*cos(x6)**2*cos(x7)*cos(x5)**3*diff(y, t)**2", "58": "83607552*M*R**2*r**2*x2**4*sin(x6)**3*sin(x7)**12*sin(x5)**2*cos(x6)**6*cos(x7)*cos(x5)**7*diff(y, t)**2", "59": "161243136*J_pz*r**2*x2**4*sin(x6)**7*sin(x7)**12*sin(x5)**7*cos(x6)**2*cos(x7)**2*cos(x5)**2*diff(x, t)*diff(y, t)", "60": "161243136*J_pz*r**2*x2**4*sin(x6)**2*sin(x7)**12*sin(x5)**2*cos(x6)**7*cos(x7)**2*cos(x5)**7*diff(x, t)*diff(y, t)", "61": "167215104*M*R**2*r**2*x2**4*sin(x6)**6*sin(x7)**12*sin(x5)**5*cos(x6)**3*cos(x7)*cos(x5)**4*diff(y, t)**2", "62": "167215104*M*R**2*r**2*x2**4*sin(x6)**4*sin(x7)**12*sin(x5)**3*cos(x6)**5*cos(x7)*cos(x5)**6*diff(y, t)**2", "63": "209018880*M*R**2*r**2*x2**4*sin(x6)**5*sin(x7)**12*sin(x5)**4*cos(x6)**4*cos(x7)*cos(x5)**5*diff(y, t)**2", "64": "376233984*J_pz*r**2*x2**4*sin(x6)**6*sin(x7)**12*sin(x5)**6*cos(x6)**3*cos(x7)**2*cos(x5)**3*diff(x, t)*diff(y, t)", "65": "376233984*J_pz*r**2*x2**4*sin(x6)**3*sin(x7)**12*sin(x5)**3*cos(x6)**6*cos(x7)**2*cos(x5)**6*diff(x, t)*diff(y, t)", "66": "564350976*J_pz*r**2*x2**4*sin(x6)**5*sin(x7)**12*sin(x5)**5*cos(x6)**4*cos(x7)**2*cos(x5)**4*diff(x, t)*diff(y, t)", "67": "564350976*J_pz*r**2*x2**4*sin(x6)**4*sin(x7)**12*sin(x5)**4*cos(x6)**5*cos(x7)**2*cos(x5)**5*diff(x, t)*diff(y, t)", "68": "-376233984*M*R**2*r**2*x2**4*sin(x6)**5*sin(x7)**13*sin(x5)**5*cos(x6)**4*cos(x7)*cos(x5)**4*diff(x, t)*diff(y, t)", "69": "-376233984*M*R**2*r**2*x2**4*sin(x6)**4*sin(x7)**13*sin(x5)**4*cos(x6)**5*cos(x7)*cos(x5)**5*diff(x, t)*diff(y, t)", "70": "-313528320*J_pz*R*r**2*x2**4*sin(x6)**4*sin(x7)**12*sin(x5)**4*cos(x6)**4*cos(x7)*cos(x5)**5*diff(y, t)*diff(x3, t)", "71": "-250822656*J_pz*R*r**2*x2**4*sin(x6)**5*sin(x7)**12*sin(x5)**5*cos(x6)**3*cos(x7)*cos(x5)**4*diff(y, t)*diff(x3, t)", "72": "-250822656*J_pz*R*r**2*x2**4*sin(x6)**3*sin(x7)**12*sin(x5)**3*cos(x6)**5*cos(x7)*cos(x5)**6*diff(y, t)*diff(x3, t)", "73": "-250822656*M*R**2*r**2*x2**4*sin(x6)**6*sin(x7)**13*sin(x5)**6*cos(x6)**3*cos(x7)*cos(x5)**3*diff(x, t)*diff(y, t)", "74": "-250822656*M*R**2*r**2*x2**4*sin(x6)**3*sin(x7)**13*sin(x5)**3*cos(x6)**6*cos(x7)*cos(x5)**6*diff(x, t)*diff(y, t)", "75": "-209018880*M*R**3*r**2*x2**4*sin(x6)**4*sin(x7)**12*sin(x5)**4*cos(x6)**4*cos(x7)*cos(x5)**5*diff(y, t)*diff(x3, t)", "76": "-167215104*M*R**3*r**2*x2**4*sin(x6)**5*sin(x7)**12*sin(x5)**5*cos(x6)**3*cos(x7)*cos(x5)**4*diff(y, t)*diff(x3, t)", "77": "-167215104*M*R**3*r**2*x2**4*sin(x6)**3*sin(x7)**12*sin(x5)**3*cos(x6)**5*cos(x7)*cos(x5)**6*diff(y, t)*diff(x3, t)", "78": "-125411328*J_pz*R*r**2*x2**4*sin(x6)**6*sin(x7)**12*sin(x5)**6*cos(x6)**2*cos(x7)*cos(x5)**3*diff(y, t)*diff(x3, t)", "79": "-125411328*J_pz*R*r**2*x2**4*sin(x6)**2*sin(x7)**12*sin(x5)**2*cos(x6)**6*cos(x7)*cos(x5)**7*diff(y, t)*diff(x3, t)", "80": "-107495424*M*R**2*r**2*x2**4*sin(x6)**7*sin(x7)**13*sin(x5)**7*cos(x6)**2*cos(x7)*cos(x5)**2*diff(x, t)*diff(y, t)", "81": "-107495424*M*R**2*r**2*x2**4*sin(x6)**2*sin(x7)**13*sin(x5)**2*cos(x6)**7*cos(x7)*cos(x5)**7*diff(x, t)*diff(y, t)", "82": "-83607552*M*R**3*r**2*x2**4*sin(x6)**6*sin(x7)**12*sin(x5)**6*cos(x6)**2*cos(x7)*cos(x5)**3*diff(y, t)*diff(x3, t)", "83": "-83607552*M*R**3*r**2*x2**4*sin(x6)**2*sin(x7)**12*sin(x5)**2*cos(x6)**6*cos(x7)*cos(x5)**7*diff(y, t)*diff(x3, t)", "84": "-35831808*J_pz*R*r**2*x2**4*sin(x6)*sin(x7)**12*sin(x5)*cos(x6)**7*cos(x7)*cos(x5)**8*diff(y, t)*diff(x3, t)", "85": "-35831808*J_pz*R*r**2*x2**4*sin(x6)**7*sin(x7)**12*sin(x5)**7*cos(x6)*cos(x7)*cos(x5)**2*diff(y, t)*diff(x3, t)", "86": "-26873856*M*R**2*r**2*x2**4*sin(x6)*sin(x7)**13*sin(x5)*cos(x6)**8*cos(x7)*cos(x5)**8*diff(x, t)*diff(y, t)", "87": "-26873856*M*R**2*r**2*x2**4*sin(x6)**8*sin(x7)**13*sin(x5)**8*cos(x6)*cos(x7)*cos(x5)*diff(x, t)*diff(y, t)", "88": "-23887872*M*R**3*r**2*x2**4*sin(x6)*sin(x7)**12*sin(x5)*cos(x6)**7*cos(x7)*cos(x5)**8*diff(y, t)*diff(x3, t)", "89": "-23887872*M*R**3*r**2*x2**4*sin(x6)**7*sin(x7)**12*sin(x5)**7*cos(x6)*cos(x7)*cos(x5)**2*diff(y, t)*diff(x3, t)", "90": "23887872*M*R**3*r**2*x2**4*sin(x6)*sin(x7)**12*sin(x5)**2*cos(x6)**7*cos(x7)*cos(x5)**7*diff(y, t)*diff(x2, t)", "91": "23887872*M*R**3*r**2*x2**4*sin(x6)**7*sin(x7)**12*sin(x5)**8*cos(x6)*cos(x7)*cos(x5)*diff(y, t)*diff(x2, t)", "92": "26873856*M*R**2*r**2*x2**4*sin(x6)*sin(x7)**12*sin(x5)*cos(x6)**8*cos(x7)**2*cos(x5)**8*diff(x, t)*diff(y, t)", "93": "26873856*M*R**2*r**2*x2**4*sin(x6)**8*sin(x7)**12*sin(x5)**8*cos(x6)*cos(x7)**2*cos(x5)*diff(x, t)*diff(y, t)", "94": "35831808*J_pz*R*r**2*x2**4*sin(x6)*sin(x7)**12*sin(x5)**2*cos(x6)**7*cos(x7)*cos(x5)**7*diff(y, t)*diff(x2, t)", "95": "35831808*J_pz*R*r**2*x2**4*sin(x6)**7*sin(x7)**12*sin(x5)**8*cos(x6)*cos(x7)*cos(x5)*diff(y, t)*diff(x2, t)", "96": "83607552*M*R**3*r**2*x2**4*sin(x6)**6*sin(x7)**12*sin(x5)**7*cos(x6)**2*cos(x7)*cos(x5)**2*diff(y, t)*diff(x2, t)", "97": "83607552*M*R**3*r**2*x2**4*sin(x6)**2*sin(x7)**12*sin(x5)**3*cos(x6)**6*cos(x7)*cos(x5)**6*diff(y, t)*diff(x2, t)", "98": "107495424*M*R**2*r**2*x2**4*sin(x6)**7*sin(x7)**12*sin(x5)**7*cos(x6)**2*cos(x7)**2*cos(x5)**2*diff(x, t)*diff(y, t)", "99": "107495424*M*R**2*r**2*x2**4*sin(x6)**2*sin(x7)**12*sin(x5)**2*cos(x6)**7*cos(x7)**2*cos(x5)**7*diff(x, t)*diff(y, t)", "100": "125411328*J_pz*R*r**2*x2**4*sin(x6)**6*sin(x7)**12*sin(x5)**7*cos(x6)**2*cos(x7)*cos(x5)**2*diff(y, t)*diff(x2, t)", "101": "125411328*J_pz*R*r**2*x2**4*sin(x6)**2*sin(x7)**12*sin(x5)**3*cos(x6)**6*cos(x7)*cos(x5)**6*diff(y, t)*diff(x2, t)", "102": "167215104*M*R**3*r**2*x2**4*sin(x6)**5*sin(x7)**12*sin(x5)**6*cos(x6)**3*cos(x7)*cos(x5)**3*diff(y, t)*diff(x2, t)", "103": "167215104*M*R**3*r**2*x2**4*sin(x6)**3*sin(x7)**12*sin(x5)**4*cos(x6)**5*cos(x7)*cos(x5)**5*diff(y, t)*diff(x2, t)", "104": "209018880*M*R**3*r**2*x2**4*sin(x6)**4*sin(x7)**12*sin(x5)**5*cos(x6)**4*cos(x7)*cos(x5)**4*diff(y, t)*diff(x2, t)", "105": "250822656*J_pz*R*r**2*x2**4*sin(x6)**5*sin(x7)**12*sin(x5)**6*cos(x6)**3*cos(x7)*cos(x5)**3*diff(y, t)*diff(x2, t)", "106": "250822656*J_pz*R*r**2*x2**4*sin(x6)**3*sin(x7)**12*sin(x5)**4*cos(x6)**5*cos(x7)*cos(x5)**5*diff(y, t)*diff(x2, t)", "107": "250822656*M*R**2*r**2*x2**4*sin(x6)**6*sin(x7)**12*sin(x5)**6*cos(x6)**3*cos(x7)**2*cos(x5)**3*diff(x, t)*diff(y, t)", "108": "250822656*M*R**2*r**2*x2**4*sin(x6)**3*sin(x7)**12*sin(x5)**3*cos(x6)**6*cos(x7)**2*cos(x5)**6*diff(x, t)*diff(y, t)", "109": "313528320*J_pz*R*r**2*x2**4*sin(x6)**4*sin(x7)**12*sin(x5)**5*cos(x6)**4*cos(x7)*cos(x5)**4*diff(y, t)*diff(x2, t)", "110": "376233984*M*R**2*r**2*x2**4*sin(x6)**5*sin(x7)**12*sin(x5)**5*cos(x6)**4*cos(x7)**2*cos(x5)**4*diff(x, t)*diff(y, t)", "111": "376233984*M*R**2*r**2*x2**4*sin(x6)**4*sin(x7)**12*sin(x5)**4*cos(x6)**5*cos(x7)**2*cos(x5)**5*diff(x, t)*diff(y, t)"}