{"0": "-128*M*R**3*r*sin(x7)*cos(x6)**2*cos(x7)*cos(x5)**3*diff(y, t)*diff(x3, t)", "1": "-128*M*R**3*r*sin(x6)**2*sin(x7)*sin(x5)**2*cos(x7)*cos(x5)*diff(y, t)*diff(x3, t)", "2": "-256*M*R**3*r*sin(x6)*sin(x7)*sin(x5)*cos(x6)*cos(x7)*cos(x5)**2*diff(y, t)*diff(x3, t)", "3": "-96*J_pz*r*sin(x7)*sin(x5)*cos(x6)**3*cos(x7)*cos(x5)**2*diff(y, t)**2", "4": "-96*J_pz*r*sin(x6)**2*sin(x7)*sin(x5)**3*cos(x6)*cos(x7)*diff(y, t)**2", "5": "96*J_pz*r*sin(x6)*sin(x7)*cos(x6)**2*cos(x7)*cos(x5)**3*diff(y, t)**2", "6": "96*J_pz*r*sin(x6)**3*sin(x7)*sin(x5)**2*cos(x7)*cos(x5)*diff(y, t)**2", "7": "-192*J_pz*r*sin(x6)*sin(x7)*sin(x5)**2*cos(x6)**2*cos(x7)*cos(x5)*diff(y, t)**2", "8": "192*J_pz*r*sin(x6)**2*sin(x7)*sin(x5)*cos(x6)*cos(x7)*cos(x5)**2*diff(y, t)**2", "9": "128*M*R**2*r*sin(x7)*cos(x6)**3*cos(x7)**2*cos(x5)**3*diff(x, t)*diff(y, t)", "10": "128*M*R**2*r*sin(x6)**3*sin(x7)*sin(x5)**3*cos(x7)**2*diff(x, t)*diff(y, t)", "11": "384*M*R**2*r*sin(x6)*sin(x7)*sin(x5)*cos(x6)**2*cos(x7)**2*cos(x5)**2*diff(x, t)*diff(y, t)", "12": "384*M*R**2*r*sin(x6)**2*sin(x7)*sin(x5)**2*cos(x6)*cos(x7)**2*cos(x5)*diff(x, t)*diff(y, t)", "13": "96*J_pz*r*sin(x7)*cos(x6)**3*cos(x7)**2*cos(x5)**3*diff(x, t)*diff(y, t)", "14": "96*J_pz*r*sin(x6)**3*sin(x7)*sin(x5)**3*cos(x7)**2*diff(x, t)*diff(y, t)", "15": "288*J_pz*r*sin(x6)*sin(x7)*sin(x5)*cos(x6)**2*cos(x7)**2*cos(x5)**2*diff(x, t)*diff(y, t)", "16": "288*J_pz*r*sin(x6)**2*sin(x7)*sin(x5)**2*cos(x6)*cos(x7)**2*cos(x5)*diff(x, t)*diff(y, t)", "17": "-128*M*R**2*r*sin(x7)*sin(x5)*cos(x6)**3*cos(x7)*cos(x5)**2*diff(y, t)**2", "18": "-128*M*R**2*r*sin(x6)**2*sin(x7)*sin(x5)**3*cos(x6)*cos(x7)*diff(y, t)**2", "19": "128*M*R**2*r*sin(x6)*sin(x7)*cos(x6)**2*cos(x7)*cos(x5)**3*diff(y, t)**2", "20": "128*M*R**2*r*sin(x6)**3*sin(x7)*sin(x5)**2*cos(x7)*cos(x5)*diff(y, t)**2", "21": "-256*M*R**2*r*sin(x6)*sin(x7)*sin(x5)**2*cos(x6)**2*cos(x7)*cos(x5)*diff(y, t)**2", "22": "256*M*R**2*r*sin(x6)**2*sin(x7)*sin(x5)*cos(x6)*cos(x7)*cos(x5)**2*diff(y, t)**2", "23": "-96*J_pz*R*r*sin(x7)*cos(x6)**2*cos(x7)*cos(x5)**3*diff(y, t)*diff(x3, t)", "24": "-96*J_pz*R*r*sin(x6)**2*sin(x7)*sin(x5)**2*cos(x7)*cos(x5)*diff(y, t)*diff(x3, t)", "25": "-192*J_pz*R*r*sin(x6)*sin(x7)*sin(x5)*cos(x6)*cos(x7)*cos(x5)**2*diff(y, t)*diff(x3, t)", "26": "128*M*R**3*r*sin(x6)**2*sin(x7)*sin(x5)**3*cos(x7)*diff(y, t)*diff(x2, t)", "27": "128*M*R**3*r*sin(x7)*sin(x5)*cos(x6)**2*cos(x7)*cos(x5)**2*diff(y, t)*diff(x2, t)", "28": "256*M*R**3*r*sin(x6)*sin(x7)*sin(x5)**2*cos(x6)*cos(x7)*cos(x5)*diff(y, t)*diff(x2, t)", "29": "96*J_pz*R*r*sin(x6)**2*sin(x7)*sin(x5)**3*cos(x7)*diff(y, t)*diff(x2, t)", "30": "96*J_pz*R*r*sin(x7)*sin(x5)*cos(x6)**2*cos(x7)*cos(x5)**2*diff(y, t)*diff(x2, t)", "31": "192*J_pz*R*r*sin(x6)*sin(x7)*sin(x5)**2*cos(x6)*cos(x7)*cos(x5)*diff(y, t)*diff(x2, t)"}